Workbook

Sheet TARIFAS Home Delivery
B1: Propuesta generada 23 - 6 - 2025. Las tarifas tienen una vigencia de 2 meses para ser aceptadas.
B3: TARIFARIO DISTRIBUCIÓN
M4: =16826+(49.1-20)*685 -> 36759.5 | N4: =M4*1.19 -> 43743.805
B6: PROPUESTA 2EBOX UM - HOME DELIVERY
B7: Tarifas Servicio EXPRESS - PRIORITY | M7: Definiciones DISTRIBUCIÓN:
B8: ORIGEN: SANTIAGO | C8: Quiebres de kilos | M8: 🔵 Las tarifas son afectas a IVA
B9: DESTINO | C9: 0 - 0.5 | D9: 0.5 - 1.5 | E9: 1.5 - 3 | F9: 3 - 6 | G9: 6 - 10 | H9: 10 - 16 | I9: 16 - 20 | J9: 20 - 50 * | K9: > 50 * | M9: 🔵 Tarifa Same Day solo para Región Metropolitana y quiebres hasta los 25 kg como máximo. En caso de sobrepasar este kilomayor máximo se cobrará un valor agregado sobre la tarifa normal.
B10: COPIAPO | C10: 4526 | D10: 4982 | E10: 5537 | F10: 6259 | G10: 7796 | H10: 9314 | I10: 10566 | J10: 541 | K10: 444 | M10: 🔵 El tarifario considera Origen SANTIAGO y Destino Comuna radio BASE. También aplica para origen y destino en la misma ciudad.
B11: LA SERENA | C11: 4244 | D11: 4672 | E11: 5192 | F11: 5869 | G11: 7201 | H11: 8604 | I11: 9767 | J11: 532 | K11: 436 | M11: 🔵 El tarifario se mantiene para un Origen regiones (Comuna Región) y entrega en SANTIAGO.
B12: OVALLE | C12: 4305 | D12: 4741 | E12: 5267 | F12: 5955 | G12: 7131 | H12: 8616 | I12: 9781 | J12: 533 | K12: 437 | M12: 🔵 Las tarifas con Origen distinto a SANTIAGO (zona radio BASE) y destino distinto a SANTIAGO se ponderan x1,2.
B13: LA CALERA | C13: 3710 | D13: 3925 | E13: 4542 | F13: 5282 | G13: 6529 | H13: 7847 | I13: 8814 | J13: 447 | K13: 376 | M13: 🔵 Tarifas con Destino una Comuna con radio INFLUENCIA tienen el mismo precio que radio BASE
B14: LOS ANDES | C14: 3673 | D14: 3886 | E14: 4496 | F14: 5230 | G14: 6465 | H14: 7769 | I14: 8731 | J14: 445 | K14: 374 | M14: 🔵 Tarifas con Destino una Comuna con radio EXTREMO (o MUY EXTREMO) se pondera x1,5
B15: VINA DEL MAR | C15: 3589 | D15: 3839 | E15: 4357 | F15: 5160 | G15: 6411 | H15: 7245 | I15: 8131 | J15: 410 | K15: 340 | M15: 🔵 Envíos a Comunas BORDER considera un costo fijo de $15000 adicional a la tarifa.
B16: SANTIAGO | C16: 2932 | D16: 3041 | E16: 3237 | F16: 3524 | G16: 4081 | H16: 4439 | I16: 5197 | J16: 300 | K16: 229 | M16: 🔵 El costo del envío está asociado al mayor valor entre el peso físico y peso volumétrico. El peso volumétrico es igual a (largo*ancho*alto)/4.000.
B17: MELIPILLA | C17: 3589 | D17: 3839 | E17: 4357 | F17: 5160 | G17: 6411 | H17: 7245 | I17: 8131 | J17: 410 | K17: 340 | M17: *Los cálculos de las tarifas sobre 20kg's y 50kg's, se calculan como kilo adicional sobre las tarifas del quiebre previo.
B18: RANCAGUA | C18: 3673 | D18: 3886 | E18: 4496 | F18: 5230 | G18: 6465 | H18: 7769 | I18: 8731 | J18: 445 | K18: 374 | M18: Ejemplo: tarifa SCL 35 kg´s = $5197 + (35 - 20)*$300.
B19: CURICO | C19: 3822 | D19: 4089 | E19: 4695 | F19: 5392 | G19: 6756 | H19: 8188 | I19: 9170 | J19: 454 | K19: 386 | M19: Ejemplo: tarifa SCL 140 kg´s = $5197 + (50 - 20)*$300 + (140 - 50)*$229.
B20: TALCA | C20: 3822 | D20: 4089 | E20: 4695 | F20: 5392 | G20: 6756 | H20: 8188 | I20: 9170 | J20: 454 | K20: 386
B21: CHILLAN | C21: 4288 | D21: 4579 | E21: 5092 | F21: 5807 | G21: 7082 | H21: 8385 | I21: 9580 | J21: 547 | K21: 441 | M21: ACLARACIONES COBROS EXTRAS:
B22: CONCEPCION | C22: 4288 | D22: 4579 | E22: 5092 | F22: 5807 | G22: 7082 | H22: 8385 | I22: 9580 | J22: 547 | K22: 441
B23: LOS ANGELES | C23: 4440 | D23: 4743 | E23: 5274 | F23: 6013 | G23: 7319 | H23: 8646 | I23: 9847 | J23: 550 | K23: 448 | M23: D.D.: Devolución de Documentos | S23: $900 + iva por Documento
B24: TEMUCO | C24: 4604 | D24: 4839 | E24: 5391 | F24: 6109 | G24: 7563 | H24: 8917 | I24: 10121 | J24: 552 | K24: 451
B25: VALDIVIA | C25: 4956 | D25: 5291 | E25: 5863 | F25: 6489 | G25: 8253 | H25: 9418 | I25: 10641 | J25: 560 | K25: 466
B26: OSORNO | C26: 4956 | D26: 5291 | E26: 5863 | F26: 6489 | G26: 8253 | H26: 9418 | I26: 10641 | J26: 560 | K26: 466
B27: PUERTO MONTT | C27: 4844 | D27: 5170 | E27: 5729 | F27: 6406 | G27: 8039 | H27: 9226 | I27: 10454 | J27: 562 | K27: 457 | M27: TERCEROS INTENTOS EN SANTIAGO Y REGIONES: Tercer intento de entrega de la carga. | S27: $1.500 + $50 por kilo
B28: CASTRO | C28: 5413 | D28: 6042 | E28: 6748 | F28: 8043 | G28: 9379 | H28: 11204 | I28: 12568 | J28: 577 | K28: 471
B30: Extremos Terrestre - Tarifas Servicio EXPRESS | M30: CUSTODIA DE CARGA STGO. Y REGIONES: Se entiende por custodia a toda solicitud de mantener carga hasta posterior coordinación de entrega. Este cobro comenzará a regir a partir del 6to día de almacenada la carga en Hub. | S30: $3.000 x posición de almacenaje x día
B31: DESTINO | C31: 0 - 0.5 | D31: 0.5 - 1.5 | E31: 1.5 - 3 | F31: 3 - 6 | G31: 6 - 10 | H31: 10 - 16 | I31: 16 - 20 | J31: 20 - 50 * | K31: > 50 *
B32: ARICA | C32: 5549 | D32: 6178 | E32: 6792 | F32: 8213 | G32: 10740 | H32: 14176 | I32: 16826 | J32: 685 | K32: 585
B33: IQUIQUE | C33: 5293 | D33: 5773 | E33: 6348 | F33: 7677 | G33: 10038 | H33: 13249 | I33: 15812 | J33: 673 | K33: 559
B34: CALAMA | C34: 5293 | D34: 5773 | E34: 6348 | F34: 7677 | G34: 10038 | H34: 13249 | I34: 15812 | J34: 673 | K34: 559
B35: ANTOFAGASTA | C35: 5081 | D35: 5432 | E35: 5971 | F35: 7220 | G35: 8990 | H35: 11867 | I35: 14235 | J35: 643 | K35: 530 | M35: CONSIDERACIONES DISTRIBUCIÓN:
B36: COYHAIQUE | C36: 5943 | D36: 6631 | E36: 7509 | F36: 9013 | G36: 11211 | H36: 14921 | I36: 17715 | J36: 737 | K36: 569 | M36: *Tarifas válidas para los movimientos de carga declarado por el cliente. Las tarifas se reajustarán semestralmente acorde a la variación que haya experimentado el Indice de Precios al Consumidor (IPC) sumado a otras variables. Estos reajustes pueden variar respecto a negociaciones futuras.
B37: PUNTA ARENAS | C37: 5943 | D37: 6631 | E37: 7509 | F37: 9013 | G37: 11211 | H37: 14921 | I37: 17715 | J37: 737 | K37: 569
B39: Extremos Aéreos - Tarifas Servicio PRIORITY
B40: DESTINO | C40: 0 - 0.5 | D40: 0.5 - 1.5 | E40: 1.5 - 3 | F40: 3 - 6 | G40: 6 - 10 | H40: 10 - 16 | I40: 16 - 20 | J40: 20 - 50 * | K40: > 50 * | M40: ** El cliente tiene un período de 3 meses para alcanzar los movimientos mensuales declarados en la negociación. En caso de incumplimiento, se podría reajustar la tarifa negociada.
B41: ARICA | C41: 6099 | D41: 7189 | E41: 8703 | F41: 10294 | G41: 17165 | H41: 26933 | I41: 31578 | J41: 1559 | K41: 1505
B42: IQUIQUE | C42: 5701 | D42: 6719 | E42: 8135 | F42: 9620 | G42: 16041 | H42: 25174 | I42: 29712 | J42: 1512 | K42: 1422
B43: CALAMA | C43: 5701 | D43: 6719 | E43: 8135 | F43: 9620 | G43: 16041 | H43: 25174 | I43: 29712 | J43: 1512 | K43: 1422 | M43: *** Este Servicio considera un seguro en la tarifa hasta los $85.000 por orden. Sobre ese valor y en caso de querer contar con seguro, se cobra un fee adicional del 0,6% del valor neto de venta del producto.
B44: ANTOFAGASTA | C44: 5517 | D44: 6381 | E44: 7728 | F44: 9139 | G44: 15240 | H44: 23914 | I44: 28296 | J44: 1443 | K44: 1346
B45: COYHAIQUE | C45: 6199 | D45: 7251 | E45: 8774 | F45: 9982 | G45: 17014 | H45: 28200 | I45: 33209 | J45: 1718 | K45: 1620
B46: PUNTA ARENAS | C46: 6199 | D46: 7251 | E46: 8774 | F46: 9982 | G46: 17014 | H46: 28200 | I46: 33209 | J46: 1718 | K46: 1620 | M46: **** La medición de plazos de entrega es por día hábil.
B48: Tarifas Servicio SAMEDAY
B49: DESTINO | C49: 0 - 0.5 | D49: 0.5 - 1.5 | E49: 1.5 - 3 | F49: 3 - 6 | G49: 6 - 10 | H49: 10 - 16 | I49: 16 - 20 | J49: 20 - 50 * | K49: > 50 *
B50: SANTIAGO | C50: 3225 | D50: 3345 | E50: 3561 | F50: 3877 | G50: 4490 | H50: 4883 | I50: 5716 | J50: 451 | K50: 451

Sheet COMUNAS - HOME DELIVERY 2026
C2: PROPUESTA 2EBOX UM - HOME DELIVERY
C3: Tarifas Servicio EXPRESS - PRIORITY
C4: ORIGEN: SANTIAGO | F4: 1 | G4: 2 | H4: 3 | I4: 4 | J4: 5 | K4: 6 | L4: 7 | M4: 8 | N4: 9
C5: REGION | D5: POSTA | E5: COMUNA DESTINO | F5: 0 - 0.5 | G5: 0.5 - 1.5 | H5: 1.5 - 3 | I5: 3 - 6 | J5: 6 - 10 | K5: 10 - 16 | L5: 16 - 20 | M5: 20 - 50 * | N5: > 50 *
C6: METROPOLITANA (XIII) | D6: SCL | E6: SANTIAGO | F6: =+'COMUNAS - HOME DELIVERY 2025'!F6*'COMUNAS - HOME DELIVERY 2025'!$Q$7 -> 3025.824 | G6: =+'COMUNAS - HOME DELIVERY 2025'!G6*'COMUNAS - HOME DELIVERY 2025'!$Q$7 -> 3138.312 | H6: =+'COMUNAS - HOME DELIVERY 2025'!H6*'COMUNAS - HOME DELIVERY 2025'!$Q$7 -> 3340.584 | I6: =+'COMUNAS - HOME DELIVERY 2025'!I6*'COMUNAS - HOME DELIVERY 2025'!$Q$7 -> 3636.768 | J6: =+'COMUNAS - HOME DELIVERY 2025'!J6*'COMUNAS - HOME DELIVERY 2025'!$Q$7 -> 4211.592 | K6: =+'COMUNAS - HOME DELIVERY 2025'!K6*'COMUNAS - HOME DELIVERY 2025'!$Q$7 -> 4581.048 | L6: =+'COMUNAS - HOME DELIVERY 2025'!L6*'COMUNAS - HOME DELIVERY 2025'!$Q$7 -> 5363.304 | M6: =+'COMUNAS - HOME DELIVERY 2025'!M6*'COMUNAS - HOME DELIVERY 2025'!$Q$7 -> 309.6 | N6: =+'COMUNAS - HOME DELIVERY 2025'!N6*'COMUNAS - HOME DELIVERY 2025'!$Q$7 -> 236.328
C7: METROPOLITANA (XIII) | D7: RLT | E7: RECOLETA | F7: =+'COMUNAS - HOME DELIVERY 2025'!F7*'COMUNAS - HOME DELIVERY 2025'!$Q$7 -> 3025.824 | G7: =+'COMUNAS - HOME DELIVERY 2025'!G7*'COMUNAS - HOME DELIVERY 2025'!$Q$7 -> 3138.312 | H7: =+'COMUNAS - HOME DELIVERY 2025'!H7*'COMUNAS - HOME DELIVERY 2025'!$Q$7 -> 3340.584 | I7: =+'COMUNAS - HOME DELIVERY 2025'!I7*'COMUNAS - HOME DELIVERY 2025'!$Q$7 -> 3636.768 | J7: =+'COMUNAS - HOME DELIVERY 2025'!J7*'COMUNAS - HOME DELIVERY 2025'!$Q$7 -> 4211.592 | K7: =+'COMUNAS - HOME DELIVERY 2025'!K7*'COMUNAS - HOME DELIVERY 2025'!$Q$7 -> 4581.048 | L7: =+'COMUNAS - HOME DELIVERY 2025'!L7*'COMUNAS - HOME DELIVERY 2025'!$Q$7 -> 5363.304 | M7: =+'COMUNAS - HOME DELIVERY 2025'!M7*'COMUNAS - HOME DELIVERY 2025'!$Q$7 -> 309.6 | N7: =+'COMUNAS - HOME DELIVERY 2025'!N7*'COMUNAS - HOME DELIVERY 2025'!$Q$7 -> 236.328
C8: METROPOLITANA (XIII) | D8: IDP | E8: INDEPENDENCIA | F8: =+'COMUNAS - HOME DELIVERY 2025'!F8*'COMUNAS - HOME DELIVERY 2025'!$Q$7 -> 3025.824 | G8: =+'COMUNAS - HOME DELIVERY 2025'!G8*'COMUNAS - HOME DELIVERY 2025'!$Q$7 -> 3138.312 | H8: =+'COMUNAS - HOME DELIVERY 2025'!H8*'COMUNAS - HOME DELIVERY 2025'!$Q$7 -> 3340.584 | I8: =+'COMUNAS - HOME DELIVERY 2025'!I8*'COMUNAS - HOME DELIVERY 2025'!$Q$7 -> 3636.768 | J8: =+'COMUNAS - HOME DELIVERY 2025'!J8*'COMUNAS - HOME DELIVERY 2025'!$Q$7 -> 4211.592 | K8: =+'COMUNAS - HOME DELIVERY 2025'!K8*'COMUNAS - HOME DELIVERY 2025'!$Q$7 -> 4581.048 | L8: =+'COMUNAS - HOME DELIVERY 2025'!L8*'COMUNAS - HOME DELIVERY 2025'!$Q$7 -> 5363.304 | M8: =+'COMUNAS - HOME DELIVERY 2025'!M8*'COMUNAS - HOME DELIVERY 2025'!$Q$7 -> 309.6 | N8: =+'COMUNAS - HOME DELIVERY 2025'!N8*'COMUNAS - HOME DELIVERY 2025'!$Q$7 -> 236.328
C9: METROPOLITANA (XIII) | D9: QTN | E9: QUINTA NORMAL | F9: =+'COMUNAS - HOME DELIVERY 2025'!F9*'COMUNAS - HOME DELIVERY 2025'!$Q$7 -> 3025.824 | G9: =+'COMUNAS - HOME DELIVERY 2025'!G9*'COMUNAS - HOME DELIVERY 2025'!$Q$7 -> 3138.312 | H9: =+'COMUNAS - HOME DELIVERY 2025'!H9*'COMUNAS - HOME DELIVERY 2025'!$Q$7 -> 3340.584 | I9: =+'COMUNAS - HOME DELIVERY 2025'!I9*'COMUNAS - HOME DELIVERY 2025'!$Q$7 -> 3636.768 | J9: =+'COMUNAS - HOME DELIVERY 2025'!J9*'COMUNAS - HOME DELIVERY 2025'!$Q$7 -> 4211.592 | K9: =+'COMUNAS - HOME DELIVERY 2025'!K9*'COMUNAS - HOME DELIVERY 2025'!$Q$7 -> 4581.048 | L9: =+'COMUNAS - HOME DELIVERY 2025'!L9*'COMUNAS - HOME DELIVERY 2025'!$Q$7 -> 5363.304 | M9: =+'COMUNAS - HOME DELIVERY 2025'!M9*'COMUNAS - HOME DELIVERY 2025'!$Q$7 -> 309.6 | N9: =+'COMUNAS - HOME DELIVERY 2025'!N9*'COMUNAS - HOME DELIVERY 2025'!$Q$7 -> 236.328
C10: METROPOLITANA (XIII) | D10: MAI | E10: MAIPU | F10: =+'COMUNAS - HOME DELIVERY 2025'!F10*'COMUNAS - HOME DELIVERY 2025'!$Q$7 -> 3025.824 | G10: =+'COMUNAS - HOME DELIVERY 2025'!G10*'COMUNAS - HOME DELIVERY 2025'!$Q$7 -> 3138.312 | H10: =+'COMUNAS - HOME DELIVERY 2025'!H10*'COMUNAS - HOME DELIVERY 2025'!$Q$7 -> 3340.584 | I10: =+'COMUNAS - HOME DELIVERY 2025'!I10*'COMUNAS - HOME DELIVERY 2025'!$Q$7 -> 3636.768 | J10: =+'COMUNAS - HOME DELIVERY 2025'!J10*'COMUNAS - HOME DELIVERY 2025'!$Q$7 -> 4211.592 | K10: =+'COMUNAS - HOME DELIVERY 2025'!K10*'COMUNAS - HOME DELIVERY 2025'!$Q$7 -> 4581.048 | L10: =+'COMUNAS - HOME DELIVERY 2025'!L10*'COMUNAS - HOME DELIVERY 2025'!$Q$7 -> 5363.304 | M10: =+'COMUNAS - HOME DELIVERY 2025'!M10*'COMUNAS - HOME DELIVERY 2025'!$Q$7 -> 309.6 | N10: =+'COMUNAS - HOME DELIVERY 2025'!N10*'COMUNAS - HOME DELIVERY 2025'!$Q$7 -> 236.328
C11: METROPOLITANA (XIII) | D11: PUD | E11: PUDAHUEL | F11: =+'COMUNAS - HOME DELIVERY 2025'!F11*'COMUNAS - HOME DELIVERY 2025'!$Q$7 -> 3025.824 | G11: =+'COMUNAS - HOME DELIVERY 2025'!G11*'COMUNAS - HOME DELIVERY 2025'!$Q$7 -> 3138.312 | H11: =+'COMUNAS - HOME DELIVERY 2025'!H11*'COMUNAS - HOME DELIVERY 2025'!$Q$7 -> 3340.584 | I11: =+'COMUNAS - HOME DELIVERY 2025'!I11*'COMUNAS - HOME DELIVERY 2025'!$Q$7 -> 3636.768 | J11: =+'COMUNAS - HOME DELIVERY 2025'!J11*'COMUNAS - HOME DELIVERY 2025'!$Q$7 -> 4211.592 | K11: =+'COMUNAS - HOME DELIVERY 2025'!K11*'COMUNAS - HOME DELIVERY 2025'!$Q$7 -> 4581.048 | L11: =+'COMUNAS - HOME DELIVERY 2025'!L11*'COMUNAS - HOME DELIVERY 2025'!$Q$7 -> 5363.304 | M11: =+'COMUNAS - HOME DELIVERY 2025'!M11*'COMUNAS - HOME DELIVERY 2025'!$Q$7 -> 309.6 | N11: =+'COMUNAS - HOME DELIVERY 2025'!N11*'COMUNAS - HOME DELIVERY 2025'!$Q$7 -> 236.328
C12: METROPOLITANA (XIII) | D12: REN | E12: RENCA | F12: =+'COMUNAS - HOME DELIVERY 2025'!F12*'COMUNAS - HOME DELIVERY 2025'!$Q$7 -> 3025.824 | G12: =+'COMUNAS - HOME DELIVERY 2025'!G12*'COMUNAS - HOME DELIVERY 2025'!$Q$7 -> 3138.312 | H12: =+'COMUNAS - HOME DELIVERY 2025'!H12*'COMUNAS - HOME DELIVERY 2025'!$Q$7 -> 3340.584 | I12: =+'COMUNAS - HOME DELIVERY 2025'!I12*'COMUNAS - HOME DELIVERY 2025'!$Q$7 -> 3636.768 | J12: =+'COMUNAS - HOME DELIVERY 2025'!J12*'COMUNAS - HOME DELIVERY 2025'!$Q$7 -> 4211.592 | K12: =+'COMUNAS - HOME DELIVERY 2025'!K12*'COMUNAS - HOME DELIVERY 2025'!$Q$7 -> 4581.048 | L12: =+'COMUNAS - HOME DELIVERY 2025'!L12*'COMUNAS - HOME DELIVERY 2025'!$Q$7 -> 5363.304 | M12: =+'COMUNAS - HOME DELIVERY 2025'!M12*'COMUNAS - HOME DELIVERY 2025'!$Q$7 -> 309.6 | N12: =+'COMUNAS - HOME DELIVERY 2025'!N12*'COMUNAS - HOME DELIVERY 2025'!$Q$7 -> 236.328
C13: METROPOLITANA (XIII) | D13: QLC | E13: QUILICURA | F13: =+'COMUNAS - HOME DELIVERY 2025'!F13*'COMUNAS - HOME DELIVERY 2025'!$Q$7 -> 3025.824 | G13: =+'COMUNAS - HOME DELIVERY 2025'!G13*'COMUNAS - HOME DELIVERY 2025'!$Q$7 -> 3138.312 | H13: =+'COMUNAS - HOME DELIVERY 2025'!H13*'COMUNAS - HOME DELIVERY 2025'!$Q$7 -> 3340.584 | I13: =+'COMUNAS - HOME DELIVERY 2025'!I13*'COMUNAS - HOME DELIVERY 2025'!$Q$7 -> 3636.768 | J13: =+'COMUNAS - HOME DELIVERY 2025'!J13*'COMUNAS - HOME DELIVERY 2025'!$Q$7 -> 4211.592 | K13: =+'COMUNAS - HOME DELIVERY 2025'!K13*'COMUNAS - HOME DELIVERY 2025'!$Q$7 -> 4581.048 | L13: =+'COMUNAS - HOME DELIVERY 2025'!L13*'COMUNAS - HOME DELIVERY 2025'!$Q$7 -> 5363.304 | M13: =+'COMUNAS - HOME DELIVERY 2025'!M13*'COMUNAS - HOME DELIVERY 2025'!$Q$7 -> 309.6 | N13: =+'COMUNAS - HOME DELIVERY 2025'!N13*'COMUNAS - HOME DELIVERY 2025'!$Q$7 -> 236.328
C14: METROPOLITANA (XIII) | D14: CNH | E14: CONCHALI | F14: =+'COMUNAS - HOME DELIVERY 2025'!F14*'COMUNAS - HOME DELIVERY 2025'!$Q$7 -> 3025.824 | G14: =+'COMUNAS - HOME DELIVERY 2025'!G14*'COMUNAS - HOME DELIVERY 2025'!$Q$7 -> 3138.312 | H14: =+'COMUNAS - HOME DELIVERY 2025'!H14*'COMUNAS - HOME DELIVERY 2025'!$Q$7 -> 3340.584 | I14: =+'COMUNAS - HOME DELIVERY 2025'!I14*'COMUNAS - HOME DELIVERY 2025'!$Q$7 -> 3636.768 | J14: =+'COMUNAS - HOME DELIVERY 2025'!J14*'COMUNAS - HOME DELIVERY 2025'!$Q$7 -> 4211.592 | K14: =+'COMUNAS - HOME DELIVERY 2025'!K14*'COMUNAS - HOME DELIVERY 2025'!$Q$7 -> 4581.048 | L14: =+'COMUNAS - HOME DELIVERY 2025'!L14*'COMUNAS - HOME DELIVERY 2025'!$Q$7 -> 5363.304 | M14: =+'COMUNAS - HOME DELIVERY 2025'!M14*'COMUNAS - HOME DELIVERY 2025'!$Q$7 -> 309.6 | N14: =+'COMUNAS - HOME DELIVERY 2025'!N14*'COMUNAS - HOME DELIVERY 2025'!$Q$7 -> 236.328
C15: METROPOLITANA (XIII) | D15: LPR | E15: LO PRADO | F15: =+'COMUNAS - HOME DELIVERY 2025'!F15*'COMUNAS - HOME DELIVERY 2025'!$Q$7 -> 3025.824 | G15: =+'COMUNAS - HOME DELIVERY 2025'!G15*'COMUNAS - HOME DELIVERY 2025'!$Q$7 -> 3138.312 | H15: =+'COMUNAS - HOME DELIVERY 2025'!H15*'COMUNAS - HOME DELIVERY 2025'!$Q$7 -> 3340.584 | I15: =+'COMUNAS - HOME DELIVERY 2025'!I15*'COMUNAS - HOME DELIVERY 2025'!$Q$7 -> 3636.768 | J15: =+'COMUNAS - HOME DELIVERY 2025'!J15*'COMUNAS - HOME DELIVERY 2025'!$Q$7 -> 4211.592 | K15: =+'COMUNAS - HOME DELIVERY 2025'!K15*'COMUNAS - HOME DELIVERY 2025'!$Q$7 -> 4581.048 | L15: =+'COMUNAS - HOME DELIVERY 2025'!L15*'COMUNAS - HOME DELIVERY 2025'!$Q$7 -> 5363.304 | M15: =+'COMUNAS - HOME DELIVERY 2025'!M15*'COMUNAS - HOME DELIVERY 2025'!$Q$7 -> 309.6 | N15: =+'COMUNAS - HOME DELIVERY 2025'!N15*'COMUNAS - HOME DELIVERY 2025'!$Q$7 -> 236.328
C16: METROPOLITANA (XIII) | D16: CNV | E16: CERRO NAVIA | F16: =+'COMUNAS - HOME DELIVERY 2025'!F16*'COMUNAS - HOME DELIVERY 2025'!$Q$7 -> 3025.824 | G16: =+'COMUNAS - HOME DELIVERY 2025'!G16*'COMUNAS - HOME DELIVERY 2025'!$Q$7 -> 3138.312 | H16: =+'COMUNAS - HOME DELIVERY 2025'!H16*'COMUNAS - HOME DELIVERY 2025'!$Q$7 -> 3340.584 | I16: =+'COMUNAS - HOME DELIVERY 2025'!I16*'COMUNAS - HOME DELIVERY 2025'!$Q$7 -> 3636.768 | J16: =+'COMUNAS - HOME DELIVERY 2025'!J16*'COMUNAS - HOME DELIVERY 2025'!$Q$7 -> 4211.592 | K16: =+'COMUNAS - HOME DELIVERY 2025'!K16*'COMUNAS - HOME DELIVERY 2025'!$Q$7 -> 4581.048 | L16: =+'COMUNAS - HOME DELIVERY 2025'!L16*'COMUNAS - HOME DELIVERY 2025'!$Q$7 -> 5363.304 | M16: =+'COMUNAS - HOME DELIVERY 2025'!M16*'COMUNAS - HOME DELIVERY 2025'!$Q$7 -> 309.6 | N16: =+'COMUNAS - HOME DELIVERY 2025'!N16*'COMUNAS - HOME DELIVERY 2025'!$Q$7 -> 236.328
C17: METROPOLITANA (XIII) | D17: ECE | E17: ESTACION CENTRAL | F17: =+'COMUNAS - HOME DELIVERY 2025'!F17*'COMUNAS - HOME DELIVERY 2025'!$Q$7 -> 3025.824 | G17: =+'COMUNAS - HOME DELIVERY 2025'!G17*'COMUNAS - HOME DELIVERY 2025'!$Q$7 -> 3138.312 | H17: =+'COMUNAS - HOME DELIVERY 2025'!H17*'COMUNAS - HOME DELIVERY 2025'!$Q$7 -> 3340.584 | I17: =+'COMUNAS - HOME DELIVERY 2025'!I17*'COMUNAS - HOME DELIVERY 2025'!$Q$7 -> 3636.768 | J17: =+'COMUNAS - HOME DELIVERY 2025'!J17*'COMUNAS - HOME DELIVERY 2025'!$Q$7 -> 4211.592 | K17: =+'COMUNAS - HOME DELIVERY 2025'!K17*'COMUNAS - HOME DELIVERY 2025'!$Q$7 -> 4581.048 | L17: =+'COMUNAS - HOME DELIVERY 2025'!L17*'COMUNAS - HOME DELIVERY 2025'!$Q$7 -> 5363.304 | M17: =+'COMUNAS - HOME DELIVERY 2025'!M17*'COMUNAS - HOME DELIVERY 2025'!$Q$7 -> 309.6 | N17: =+'COMUNAS - HOME DELIVERY 2025'!N17*'COMUNAS - HOME DELIVERY 2025'!$Q$7 -> 236.328
... C310: LOS LAGOS (X) | D310: SPL | E310: SAN PABLO | F310: =+'COMUNAS - HOME DELIVERY 2025'!F310*'COMUNAS - HOME DELIVERY 2025'!$Q$7 -> 5114.592 | G310: =+'COMUNAS - HOME DELIVERY 2025'!G310*'COMUNAS - HOME DELIVERY 2025'!$Q$7 -> 5460.312 | H310: =+'COMUNAS - HOME DELIVERY 2025'!H310*'COMUNAS - HOME DELIVERY 2025'!$Q$7 -> 6050.616 | I310: =+'COMUNAS - HOME DELIVERY 2025'!I310*'COMUNAS - HOME DELIVERY 2025'!$Q$7 -> 6696.648 | J310: =+'COMUNAS - HOME DELIVERY 2025'!J310*'COMUNAS - HOME DELIVERY 2025'!$Q$7 -> 8517.096 | K310: =+'COMUNAS - HOME DELIVERY 2025'!K310*'COMUNAS - HOME DELIVERY 2025'!$Q$7 -> 9719.376 | L310: =+'COMUNAS - HOME DELIVERY 2025'!L310*'COMUNAS - HOME DELIVERY 2025'!$Q$7 -> 10981.512 | M310: =+'COMUNAS - HOME DELIVERY 2025'!M310*'COMUNAS - HOME DELIVERY 2025'!$Q$7 -> 577.92 | N310: =+'COMUNAS - HOME DELIVERY 2025'!N310*'COMUNAS - HOME DELIVERY 2025'!$Q$7 -> 480.912
C311: Extremos Aéreos - Tarifas Servicio PRIORITY
C312: REGION | D312: POSTA | E312: COMUNA DESTINO | F312: 0 - 0.5 | G312: 0.5 - 1.5 | H312: 1.5 - 3 | I312: 3 - 6 | J312: 6 - 10 | K312: 10 - 16 | L312: 16 - 20 | M312: 20 - 50 * | N312: > 50 *
C313: ARICA Y PARINACOTA (XV) | D313: ARI | E313: ARICA | F313: =+'COMUNAS - HOME DELIVERY 2025'!F313*'COMUNAS - HOME DELIVERY 2025'!$Q$7 -> 6294.168 | G313: =+'COMUNAS - HOME DELIVERY 2025'!G313*'COMUNAS - HOME DELIVERY 2025'!$Q$7 -> 7419.048 | H313: =+'COMUNAS - HOME DELIVERY 2025'!H313*'COMUNAS - HOME DELIVERY 2025'!$Q$7 -> 8981.496 | I313: =+'COMUNAS - HOME DELIVERY 2025'!I313*'COMUNAS - HOME DELIVERY 2025'!$Q$7 -> 10623.408 | J313: =+'COMUNAS - HOME DELIVERY 2025'!J313*'COMUNAS - HOME DELIVERY 2025'!$Q$7 -> 17714.28 | K313: =+'COMUNAS - HOME DELIVERY 2025'!K313*'COMUNAS - HOME DELIVERY 2025'!$Q$7 -> 27794.856 | L313: =+'COMUNAS - HOME DELIVERY 2025'!L313*'COMUNAS - HOME DELIVERY 2025'!$Q$7 -> 32588.496 | M313: =+'COMUNAS - HOME DELIVERY 2025'!M313*'COMUNAS - HOME DELIVERY 2025'!$Q$7 -> 1608.888 | N313: =+'COMUNAS - HOME DELIVERY 2025'!N313*'COMUNAS - HOME DELIVERY 2025'!$Q$7 -> 1553.16
C314: ARICA Y PARINACOTA (XV) | D314: CAM | E314: CAMARONES | F314: =+'COMUNAS - HOME DELIVERY 2025'!F314*'COMUNAS - HOME DELIVERY 2025'!$Q$7 -> 24921.252 | G314: =+'COMUNAS - HOME DELIVERY 2025'!G314*'COMUNAS - HOME DELIVERY 2025'!$Q$7 -> 26608.572 | H314: =+'COMUNAS - HOME DELIVERY 2025'!H314*'COMUNAS - HOME DELIVERY 2025'!$Q$7 -> 28952.244 | I314: =+'COMUNAS - HOME DELIVERY 2025'!I314*'COMUNAS - HOME DELIVERY 2025'!$Q$7 -> 31415.112 | J314: =+'COMUNAS - HOME DELIVERY 2025'!J314*'COMUNAS - HOME DELIVERY 2025'!$Q$7 -> 42051.42 | K314: =+'COMUNAS - HOME DELIVERY 2025'!K314*'COMUNAS - HOME DELIVERY 2025'!$Q$7 -> 57172.284 | L314: =+'COMUNAS - HOME DELIVERY 2025'!L314*'COMUNAS - HOME DELIVERY 2025'!$Q$7 -> 64362.744 | M314: =+'COMUNAS - HOME DELIVERY 2025'!M314*'COMUNAS - HOME DELIVERY 2025'!$Q$7 -> 2413.332 | N314: =+'COMUNAS - HOME DELIVERY 2025'!N314*'COMUNAS - HOME DELIVERY 2025'!$Q$7 -> 2329.74
C315: ARICA Y PARINACOTA (XV) | D315: LGR | E315: GENERAL LAGOS | F315: =+'COMUNAS - HOME DELIVERY 2025'!F315*'COMUNAS - HOME DELIVERY 2025'!$Q$7 -> 24921.252 | G315: =+'COMUNAS - HOME DELIVERY 2025'!G315*'COMUNAS - HOME DELIVERY 2025'!$Q$7 -> 26608.572 | H315: =+'COMUNAS - HOME DELIVERY 2025'!H315*'COMUNAS - HOME DELIVERY 2025'!$Q$7 -> 28952.244 | I315: =+'COMUNAS - HOME DELIVERY 2025'!I315*'COMUNAS - HOME DELIVERY 2025'!$Q$7 -> 31415.112 | J315: =+'COMUNAS - HOME DELIVERY 2025'!J315*'COMUNAS - HOME DELIVERY 2025'!$Q$7 -> 42051.42 | K315: =+'COMUNAS - HOME DELIVERY 2025'!K315*'COMUNAS - HOME DELIVERY 2025'!$Q$7 -> 57172.284 | L315: =+'COMUNAS - HOME DELIVERY 2025'!L315*'COMUNAS - HOME DELIVERY 2025'!$Q$7 -> 64362.744 | M315: =+'COMUNAS - HOME DELIVERY 2025'!M315*'COMUNAS - HOME DELIVERY 2025'!$Q$7 -> 2413.332 | N315: =+'COMUNAS - HOME DELIVERY 2025'!N315*'COMUNAS - HOME DELIVERY 2025'!$Q$7 -> 2329.74
C316: ARICA Y PARINACOTA (XV) | D316: PTR | E316: PUTRE | F316: =+'COMUNAS - HOME DELIVERY 2025'!F316*'COMUNAS - HOME DELIVERY 2025'!$Q$7 -> 24921.252 | G316: =+'COMUNAS - HOME DELIVERY 2025'!G316*'COMUNAS - HOME DELIVERY 2025'!$Q$7 -> 26608.572 | H316: =+'COMUNAS - HOME DELIVERY 2025'!H316*'COMUNAS - HOME DELIVERY 2025'!$Q$7 -> 28952.244 | I316: =+'COMUNAS - HOME DELIVERY 2025'!I316*'COMUNAS - HOME DELIVERY 2025'!$Q$7 -> 31415.112 | J316: =+'COMUNAS - HOME DELIVERY 2025'!J316*'COMUNAS - HOME DELIVERY 2025'!$Q$7 -> 42051.42 | K316: =+'COMUNAS - HOME DELIVERY 2025'!K316*'COMUNAS - HOME DELIVERY 2025'!$Q$7 -> 57172.284 | L316: =+'COMUNAS - HOME DELIVERY 2025'!L316*'COMUNAS - HOME DELIVERY 2025'!$Q$7 -> 64362.744 | M316: =+'COMUNAS - HOME DELIVERY 2025'!M316*'COMUNAS - HOME DELIVERY 2025'!$Q$7 -> 2413.332 | N316: =+'COMUNAS - HOME DELIVERY 2025'!N316*'COMUNAS - HOME DELIVERY 2025'!$Q$7 -> 2329.74
C317: TARAPACA (I) | D317: IQQ | E317: IQUIQUE | F317: =+'COMUNAS - HOME DELIVERY 2025'!F317*'COMUNAS - HOME DELIVERY 2025'!$Q$7 -> 5883.432 | G317: =+'COMUNAS - HOME DELIVERY 2025'!G317*'COMUNAS - HOME DELIVERY 2025'!$Q$7 -> 6934.008 | H317: =+'COMUNAS - HOME DELIVERY 2025'!H317*'COMUNAS - HOME DELIVERY 2025'!$Q$7 -> 8395.32 | I317: =+'COMUNAS - HOME DELIVERY 2025'!I317*'COMUNAS - HOME DELIVERY 2025'!$Q$7 -> 9927.84 | J317: =+'COMUNAS - HOME DELIVERY 2025'!J317*'COMUNAS - HOME DELIVERY 2025'!$Q$7 -> 16554.312 | K317: =+'COMUNAS - HOME DELIVERY 2025'!K317*'COMUNAS - HOME DELIVERY 2025'!$Q$7 -> 25979.568 | L317: =+'COMUNAS - HOME DELIVERY 2025'!L317*'COMUNAS - HOME DELIVERY 2025'!$Q$7 -> 30662.784 | M317: =+'COMUNAS - HOME DELIVERY 2025'!M317*'COMUNAS - HOME DELIVERY 2025'!$Q$7 -> 1560.384 | N317: =+'COMUNAS - HOME DELIVERY 2025'!N317*'COMUNAS - HOME DELIVERY 2025'!$Q$7 -> 1467.504
C318: TARAPACA (I) | D318: AHP | E318: ALTO HOSPICIO | F318: =+'COMUNAS - HOME DELIVERY 2025'!F318*'COMUNAS - HOME DELIVERY 2025'!$Q$7 -> 5883.432 | G318: =+'COMUNAS - HOME DELIVERY 2025'!G318*'COMUNAS - HOME DELIVERY 2025'!$Q$7 -> 6934.008 | H318: =+'COMUNAS - HOME DELIVERY 2025'!H318*'COMUNAS - HOME DELIVERY 2025'!$Q$7 -> 8395.32 | I318: =+'COMUNAS - HOME DELIVERY 2025'!I318*'COMUNAS - HOME DELIVERY 2025'!$Q$7 -> 9927.84 | J318: =+'COMUNAS - HOME DELIVERY 2025'!J318*'COMUNAS - HOME DELIVERY 2025'!$Q$7 -> 16554.312 | K318: =+'COMUNAS - HOME DELIVERY 2025'!K318*'COMUNAS - HOME DELIVERY 2025'!$Q$7 -> 25979.568 | L318: =+'COMUNAS - HOME DELIVERY 2025'!L318*'COMUNAS - HOME DELIVERY 2025'!$Q$7 -> 30662.784 | M318: =+'COMUNAS - HOME DELIVERY 2025'!M318*'COMUNAS - HOME DELIVERY 2025'!$Q$7 -> 1560.384 | N318: =+'COMUNAS - HOME DELIVERY 2025'!N318*'COMUNAS - HOME DELIVERY 2025'!$Q$7 -> 1467.504
C319: TARAPACA (I) | D319: CMN | E319: CAMINA | F319: =+'COMUNAS - HOME DELIVERY 2025'!F319*'COMUNAS - HOME DELIVERY 2025'!$Q$7 -> 24305.148 | G319: =+'COMUNAS - HOME DELIVERY 2025'!G319*'COMUNAS - HOME DELIVERY 2025'!$Q$7 -> 25881.012 | H319: =+'COMUNAS - HOME DELIVERY 2025'!H319*'COMUNAS - HOME DELIVERY 2025'!$Q$7 -> 28072.98 | I319: =+'COMUNAS - HOME DELIVERY 2025'!I319*'COMUNAS - HOME DELIVERY 2025'!$Q$7 -> 30371.76 | J319: =+'COMUNAS - HOME DELIVERY 2025'!J319*'COMUNAS - HOME DELIVERY 2025'!$Q$7 -> 40311.468 | K319: =+'COMUNAS - HOME DELIVERY 2025'!K319*'COMUNAS - HOME DELIVERY 2025'!$Q$7 -> 54449.352 | L319: =+'COMUNAS - HOME DELIVERY 2025'!L319*'COMUNAS - HOME DELIVERY 2025'!$Q$7 -> 61474.176 | M319: =+'COMUNAS - HOME DELIVERY 2025'!M319*'COMUNAS - HOME DELIVERY 2025'!$Q$7 -> 2340.576 | N319: =+'COMUNAS - HOME DELIVERY 2025'!N319*'COMUNAS - HOME DELIVERY 2025'!$Q$7 -> 2201.256
C320: TARAPACA (I) | D320: COE | E320: COLCHANE | F320: =+'COMUNAS - HOME DELIVERY 2025'!F320*'COMUNAS - HOME DELIVERY 2025'!$Q$7 -> 24305.148 | G320: =+'COMUNAS - HOME DELIVERY 2025'!G320*'COMUNAS - HOME DELIVERY 2025'!$Q$7 -> 25881.012 | H320: =+'COMUNAS - HOME DELIVERY 2025'!H320*'COMUNAS - HOME DELIVERY 2025'!$Q$7 -> 28072.98 | I320: =+'COMUNAS - HOME DELIVERY 2025'!I320*'COMUNAS - HOME DELIVERY 2025'!$Q$7 -> 30371.76 | J320: =+'COMUNAS - HOME DELIVERY 2025'!J320*'COMUNAS - HOME DELIVERY 2025'!$Q$7 -> 40311.468 | K320: =+'COMUNAS - HOME DELIVERY 2025'!K320*'COMUNAS - HOME DELIVERY 2025'!$Q$7 -> 54449.352 | L320: =+'COMUNAS - HOME DELIVERY 2025'!L320*'COMUNAS - HOME DELIVERY 2025'!$Q$7 -> 61474.176 | M320: =+'COMUNAS - HOME DELIVERY 2025'!M320*'COMUNAS - HOME DELIVERY 2025'!$Q$7 -> 2340.576 | N320: =+'COMUNAS - HOME DELIVERY 2025'!N320*'COMUNAS - HOME DELIVERY 2025'!$Q$7 -> 2201.256
C321: TARAPACA (I) | D321: HRA | E321: HUARA | F321: =+'COMUNAS - HOME DELIVERY 2025'!F321*'COMUNAS - HOME DELIVERY 2025'!$Q$7 -> 8825.148 | G321: =+'COMUNAS - HOME DELIVERY 2025'!G321*'COMUNAS - HOME DELIVERY 2025'!$Q$7 -> 10401.012 | H321: =+'COMUNAS - HOME DELIVERY 2025'!H321*'COMUNAS - HOME DELIVERY 2025'!$Q$7 -> 12592.98 | I321: =+'COMUNAS - HOME DELIVERY 2025'!I321*'COMUNAS - HOME DELIVERY 2025'!$Q$7 -> 14891.76 | J321: =+'COMUNAS - HOME DELIVERY 2025'!J321*'COMUNAS - HOME DELIVERY 2025'!$Q$7 -> 24831.468 | K321: =+'COMUNAS - HOME DELIVERY 2025'!K321*'COMUNAS - HOME DELIVERY 2025'!$Q$7 -> 38969.352 | L321: =+'COMUNAS - HOME DELIVERY 2025'!L321*'COMUNAS - HOME DELIVERY 2025'!$Q$7 -> 45994.176 | M321: =+'COMUNAS - HOME DELIVERY 2025'!M321*'COMUNAS - HOME DELIVERY 2025'!$Q$7 -> 2340.576 | N321: =+'COMUNAS - HOME DELIVERY 2025'!N321*'COMUNAS - HOME DELIVERY 2025'!$Q$7 -> 2201.256
C322: TARAPACA (I) | D322: OPC | E322: PICA | F322: =+'COMUNAS - HOME DELIVERY 2025'!F322*'COMUNAS - HOME DELIVERY 2025'!$Q$7 -> 8825.148 | G322: =+'COMUNAS - HOME DELIVERY 2025'!G322*'COMUNAS - HOME DELIVERY 2025'!$Q$7 -> 10401.012 | H322: =+'COMUNAS - HOME DELIVERY 2025'!H322*'COMUNAS - HOME DELIVERY 2025'!$Q$7 -> 12592.98 | I322: =+'COMUNAS - HOME DELIVERY 2025'!I322*'COMUNAS - HOME DELIVERY 2025'!$Q$7 -> 14891.76 | J322: =+'COMUNAS - HOME DELIVERY 2025'!J322*'COMUNAS - HOME DELIVERY 2025'!$Q$7 -> 24831.468 | K322: =+'COMUNAS - HOME DELIVERY 2025'!K322*'COMUNAS - HOME DELIVERY 2025'!$Q$7 -> 38969.352 | L322: =+'COMUNAS - HOME DELIVERY 2025'!L322*'COMUNAS - HOME DELIVERY 2025'!$Q$7 -> 45994.176 | M322: =+'COMUNAS - HOME DELIVERY 2025'!M322*'COMUNAS - HOME DELIVERY 2025'!$Q$7 -> 2340.576 | N322: =+'COMUNAS - HOME DELIVERY 2025'!N322*'COMUNAS - HOME DELIVERY 2025'!$Q$7 -> 2201.256
C323: TARAPACA (I) | D323: PAM | E323: POZO ALMONTE | F323: =+'COMUNAS - HOME DELIVERY 2025'!F323*'COMUNAS - HOME DELIVERY 2025'!$Q$7 -> 8825.148 | G323: =+'COMUNAS - HOME DELIVERY 2025'!G323*'COMUNAS - HOME DELIVERY 2025'!$Q$7 -> 10401.012 | H323: =+'COMUNAS - HOME DELIVERY 2025'!H323*'COMUNAS - HOME DELIVERY 2025'!$Q$7 -> 12592.98 | I323: =+'COMUNAS - HOME DELIVERY 2025'!I323*'COMUNAS - HOME DELIVERY 2025'!$Q$7 -> 14891.76 | J323: =+'COMUNAS - HOME DELIVERY 2025'!J323*'COMUNAS - HOME DELIVERY 2025'!$Q$7 -> 24831.468 | K323: =+'COMUNAS - HOME DELIVERY 2025'!K323*'COMUNAS - HOME DELIVERY 2025'!$Q$7 -> 38969.352 | L323: =+'COMUNAS - HOME DELIVERY 2025'!L323*'COMUNAS - HOME DELIVERY 2025'!$Q$7 -> 45994.176 | M323: =+'COMUNAS - HOME DELIVERY 2025'!M323*'COMUNAS - HOME DELIVERY 2025'!$Q$7 -> 2340.576 | N323: =+'COMUNAS - HOME DELIVERY 2025'!N323*'COMUNAS - HOME DELIVERY 2025'!$Q$7 -> 2201.256
C324: ANTOFAGASTA (II) | D324: ANF | E324: ANTOFAGASTA | F324: =+'COMUNAS - HOME DELIVERY 2025'!F324*'COMUNAS - HOME DELIVERY 2025'!$Q$7 -> 5693.544 | G324: =+'COMUNAS - HOME DELIVERY 2025'!G324*'COMUNAS - HOME DELIVERY 2025'!$Q$7 -> 6585.192 | H324: =+'COMUNAS - HOME DELIVERY 2025'!H324*'COMUNAS - HOME DELIVERY 2025'!$Q$7 -> 7975.296 | I324: =+'COMUNAS - HOME DELIVERY 2025'!I324*'COMUNAS - HOME DELIVERY 2025'!$Q$7 -> 9431.448 | J324: =+'COMUNAS - HOME DELIVERY 2025'!J324*'COMUNAS - HOME DELIVERY 2025'!$Q$7 -> 15727.68 | K324: =+'COMUNAS - HOME DELIVERY 2025'!K324*'COMUNAS - HOME DELIVERY 2025'!$Q$7 -> 24679.248 | L324: =+'COMUNAS - HOME DELIVERY 2025'!L324*'COMUNAS - HOME DELIVERY 2025'!$Q$7 -> 29201.472 | M324: =+'COMUNAS - HOME DELIVERY 2025'!M324*'COMUNAS - HOME DELIVERY 2025'!$Q$7 -> 1489.176 | N324: =+'COMUNAS - HOME DELIVERY 2025'!N324*'COMUNAS - HOME DELIVERY 2025'!$Q$7 -> 1389.072
... C353: MAGALLANES (XII) | D353: ATC | E353: ANTARTICA | F353: =+'COMUNAS - HOME DELIVERY 2025'!F353*'COMUNAS - HOME DELIVERY 2025'!$Q$7 -> 25076.052 | G353: =+'COMUNAS - HOME DELIVERY 2025'!G353*'COMUNAS - HOME DELIVERY 2025'!$Q$7 -> 26704.548 | H353: =+'COMUNAS - HOME DELIVERY 2025'!H353*'COMUNAS - HOME DELIVERY 2025'!$Q$7 -> 29062.152 | I353: =+'COMUNAS - HOME DELIVERY 2025'!I353*'COMUNAS - HOME DELIVERY 2025'!$Q$7 -> 30932.136 | J353: =+'COMUNAS - HOME DELIVERY 2025'!J353*'COMUNAS - HOME DELIVERY 2025'!$Q$7 -> 41817.672 | K353: =+'COMUNAS - HOME DELIVERY 2025'!K353*'COMUNAS - HOME DELIVERY 2025'!$Q$7 -> 59133.6 | L353: =+'COMUNAS - HOME DELIVERY 2025'!L353*'COMUNAS - HOME DELIVERY 2025'!$Q$7 -> 66887.532 | M353: =+'COMUNAS - HOME DELIVERY 2025'!M353*'COMUNAS - HOME DELIVERY 2025'!$Q$7 -> 2659.464 | N353: =+'COMUNAS - HOME DELIVERY 2025'!N353*'COMUNAS - HOME DELIVERY 2025'!$Q$7 -> 2507.76
C355: Extremos Terrestre - Tarifas Servicio EXPRESS
C356: REGION | D356: POSTA | E356: COMUNA DESTINO | F356: 0 - 0.5 | G356: 0.5 - 1.5 | H356: 1.5 - 3 | I356: 3 - 6 | J356: 6 - 10 | K356: 10 - 16 | L356: 16 - 20 | M356: 20 - 50 * | N356: > 50 *
C357: ARICA Y PARINACOTA (XV) | D357: ARI | E357: ARICA | F357: =+'COMUNAS - HOME DELIVERY 2025'!F357*'COMUNAS - HOME DELIVERY 2025'!$Q$7 -> 5726.568 | G357: =+'COMUNAS - HOME DELIVERY 2025'!G357*'COMUNAS - HOME DELIVERY 2025'!$Q$7 -> 6375.696 | H357: =+'COMUNAS - HOME DELIVERY 2025'!H357*'COMUNAS - HOME DELIVERY 2025'!$Q$7 -> 7009.344 | I357: =+'COMUNAS - HOME DELIVERY 2025'!I357*'COMUNAS - HOME DELIVERY 2025'!$Q$7 -> 8475.816 | J357: =+'COMUNAS - HOME DELIVERY 2025'!J357*'COMUNAS - HOME DELIVERY 2025'!$Q$7 -> 11083.68 | K357: =+'COMUNAS - HOME DELIVERY 2025'!K357*'COMUNAS - HOME DELIVERY 2025'!$Q$7 -> 14629.632 | L357: =+'COMUNAS - HOME DELIVERY 2025'!L357*'COMUNAS - HOME DELIVERY 2025'!$Q$7 -> 17364.432 | M357: =+'COMUNAS - HOME DELIVERY 2025'!M357*'COMUNAS - HOME DELIVERY 2025'!$Q$7 -> 706.92 | N357: =+'COMUNAS - HOME DELIVERY 2025'!N357*'COMUNAS - HOME DELIVERY 2025'!$Q$7 -> 603.72
C358: ARICA Y PARINACOTA (XV) | D358: CAM | E358: CAMARONES | F358: =+'COMUNAS - HOME DELIVERY 2025'!F358*'COMUNAS - HOME DELIVERY 2025'!$Q$7 -> 24069.852 | G358: =+'COMUNAS - HOME DELIVERY 2025'!G358*'COMUNAS - HOME DELIVERY 2025'!$Q$7 -> 25043.544 | H358: =+'COMUNAS - HOME DELIVERY 2025'!H358*'COMUNAS - HOME DELIVERY 2025'!$Q$7 -> 25994.016 | I358: =+'COMUNAS - HOME DELIVERY 2025'!I358*'COMUNAS - HOME DELIVERY 2025'!$Q$7 -> 28193.724 | J358: =+'COMUNAS - HOME DELIVERY 2025'!J358*'COMUNAS - HOME DELIVERY 2025'!$Q$7 -> 32105.52 | K358: =+'COMUNAS - HOME DELIVERY 2025'!K358*'COMUNAS - HOME DELIVERY 2025'!$Q$7 -> 37424.448 | L358: =+'COMUNAS - HOME DELIVERY 2025'!L358*'COMUNAS - HOME DELIVERY 2025'!$Q$7 -> 41526.648 | M358: =+'COMUNAS - HOME DELIVERY 2025'!M358*'COMUNAS - HOME DELIVERY 2025'!$Q$7 -> 1060.38 | N358: =+'COMUNAS - HOME DELIVERY 2025'!N358*'COMUNAS - HOME DELIVERY 2025'!$Q$7 -> 905.58
C359: ARICA Y PARINACOTA (XV) | D359: LGR | E359: GENERAL LAGOS | F359: =+'COMUNAS - HOME DELIVERY 2025'!F359*'COMUNAS - HOME DELIVERY 2025'!$Q$7 -> 24069.852 | G359: =+'COMUNAS - HOME DELIVERY 2025'!G359*'COMUNAS - HOME DELIVERY 2025'!$Q$7 -> 25043.544 | H359: =+'COMUNAS - HOME DELIVERY 2025'!H359*'COMUNAS - HOME DELIVERY 2025'!$Q$7 -> 25994.016 | I359: =+'COMUNAS - HOME DELIVERY 2025'!I359*'COMUNAS - HOME DELIVERY 2025'!$Q$7 -> 28193.724 | J359: =+'COMUNAS - HOME DELIVERY 2025'!J359*'COMUNAS - HOME DELIVERY 2025'!$Q$7 -> 32105.52 | K359: =+'COMUNAS - HOME DELIVERY 2025'!K359*'COMUNAS - HOME DELIVERY 2025'!$Q$7 -> 37424.448 | L359: =+'COMUNAS - HOME DELIVERY 2025'!L359*'COMUNAS - HOME DELIVERY 2025'!$Q$7 -> 41526.648 | M359: =+'COMUNAS - HOME DELIVERY 2025'!M359*'COMUNAS - HOME DELIVERY 2025'!$Q$7 -> 1060.38 | N359: =+'COMUNAS - HOME DELIVERY 2025'!N359*'COMUNAS - HOME DELIVERY 2025'!$Q$7 -> 905.58
C360: ARICA Y PARINACOTA (XV) | D360: PTR | E360: PUTRE | F360: =+'COMUNAS - HOME DELIVERY 2025'!F360*'COMUNAS - HOME DELIVERY 2025'!$Q$7 -> 24069.852 | G360: =+'COMUNAS - HOME DELIVERY 2025'!G360*'COMUNAS - HOME DELIVERY 2025'!$Q$7 -> 25043.544 | H360: =+'COMUNAS - HOME DELIVERY 2025'!H360*'COMUNAS - HOME DELIVERY 2025'!$Q$7 -> 25994.016 | I360: =+'COMUNAS - HOME DELIVERY 2025'!I360*'COMUNAS - HOME DELIVERY 2025'!$Q$7 -> 28193.724 | J360: =+'COMUNAS - HOME DELIVERY 2025'!J360*'COMUNAS - HOME DELIVERY 2025'!$Q$7 -> 32105.52 | K360: =+'COMUNAS - HOME DELIVERY 2025'!K360*'COMUNAS - HOME DELIVERY 2025'!$Q$7 -> 37424.448 | L360: =+'COMUNAS - HOME DELIVERY 2025'!L360*'COMUNAS - HOME DELIVERY 2025'!$Q$7 -> 41526.648 | M360: =+'COMUNAS - HOME DELIVERY 2025'!M360*'COMUNAS - HOME DELIVERY 2025'!$Q$7 -> 1060.38 | N360: =+'COMUNAS - HOME DELIVERY 2025'!N360*'COMUNAS - HOME DELIVERY 2025'!$Q$7 -> 905.58
C361: TARAPACA (I) | D361: IQQ | E361: IQUIQUE | F361: =+'COMUNAS - HOME DELIVERY 2025'!F361*'COMUNAS - HOME DELIVERY 2025'!$Q$7 -> 5462.376 | G361: =+'COMUNAS - HOME DELIVERY 2025'!G361*'COMUNAS - HOME DELIVERY 2025'!$Q$7 -> 5957.736 | H361: =+'COMUNAS - HOME DELIVERY 2025'!H361*'COMUNAS - HOME DELIVERY 2025'!$Q$7 -> 6551.136 | I361: =+'COMUNAS - HOME DELIVERY 2025'!I361*'COMUNAS - HOME DELIVERY 2025'!$Q$7 -> 7922.664 | J361: =+'COMUNAS - HOME DELIVERY 2025'!J361*'COMUNAS - HOME DELIVERY 2025'!$Q$7 -> 10359.216 | K361: =+'COMUNAS - HOME DELIVERY 2025'!K361*'COMUNAS - HOME DELIVERY 2025'!$Q$7 -> 13672.968 | L361: =+'COMUNAS - HOME DELIVERY 2025'!L361*'COMUNAS - HOME DELIVERY 2025'!$Q$7 -> 16317.984 | M361: =+'COMUNAS - HOME DELIVERY 2025'!M361*'COMUNAS - HOME DELIVERY 2025'!$Q$7 -> 694.536 | N361: =+'COMUNAS - HOME DELIVERY 2025'!N361*'COMUNAS - HOME DELIVERY 2025'!$Q$7 -> 576.888
C362: TARAPACA (I) | D362: AHP | E362: ALTO HOSPICIO | F362: =+'COMUNAS - HOME DELIVERY 2025'!F362*'COMUNAS - HOME DELIVERY 2025'!$Q$7 -> 5462.376 | G362: =+'COMUNAS - HOME DELIVERY 2025'!G362*'COMUNAS - HOME DELIVERY 2025'!$Q$7 -> 5957.736 | H362: =+'COMUNAS - HOME DELIVERY 2025'!H362*'COMUNAS - HOME DELIVERY 2025'!$Q$7 -> 6551.136 | I362: =+'COMUNAS - HOME DELIVERY 2025'!I362*'COMUNAS - HOME DELIVERY 2025'!$Q$7 -> 7922.664 | J362: =+'COMUNAS - HOME DELIVERY 2025'!J362*'COMUNAS - HOME DELIVERY 2025'!$Q$7 -> 10359.216 | K362: =+'COMUNAS - HOME DELIVERY 2025'!K362*'COMUNAS - HOME DELIVERY 2025'!$Q$7 -> 13672.968 | L362: =+'COMUNAS - HOME DELIVERY 2025'!L362*'COMUNAS - HOME DELIVERY 2025'!$Q$7 -> 16317.984 | M362: =+'COMUNAS - HOME DELIVERY 2025'!M362*'COMUNAS - HOME DELIVERY 2025'!$Q$7 -> 694.536 | N362: =+'COMUNAS - HOME DELIVERY 2025'!N362*'COMUNAS - HOME DELIVERY 2025'!$Q$7 -> 576.888
C363: TARAPACA (I) | D363: CMN | E363: CAMINA | F363: =+'COMUNAS - HOME DELIVERY 2025'!F363*'COMUNAS - HOME DELIVERY 2025'!$Q$7 -> 23673.564 | G363: =+'COMUNAS - HOME DELIVERY 2025'!G363*'COMUNAS - HOME DELIVERY 2025'!$Q$7 -> 24416.604 | H363: =+'COMUNAS - HOME DELIVERY 2025'!H363*'COMUNAS - HOME DELIVERY 2025'!$Q$7 -> 25306.704 | I363: =+'COMUNAS - HOME DELIVERY 2025'!I363*'COMUNAS - HOME DELIVERY 2025'!$Q$7 -> 27363.996 | J363: =+'COMUNAS - HOME DELIVERY 2025'!J363*'COMUNAS - HOME DELIVERY 2025'!$Q$7 -> 31018.824 | K363: =+'COMUNAS - HOME DELIVERY 2025'!K363*'COMUNAS - HOME DELIVERY 2025'!$Q$7 -> 35989.452 | L363: =+'COMUNAS - HOME DELIVERY 2025'!L363*'COMUNAS - HOME DELIVERY 2025'!$Q$7 -> 39956.976 | M363: =+'COMUNAS - HOME DELIVERY 2025'!M363*'COMUNAS - HOME DELIVERY 2025'!$Q$7 -> 1041.804 | N363: =+'COMUNAS - HOME DELIVERY 2025'!N363*'COMUNAS - HOME DELIVERY 2025'!$Q$7 -> 865.332
C364: TARAPACA (I) | D364: COE | E364: COLCHANE | F364: =+'COMUNAS - HOME DELIVERY 2025'!F364*'COMUNAS - HOME DELIVERY 2025'!$Q$7 -> 23673.564 | G364: =+'COMUNAS - HOME DELIVERY 2025'!G364*'COMUNAS - HOME DELIVERY 2025'!$Q$7 -> 24416.604 | H364: =+'COMUNAS - HOME DELIVERY 2025'!H364*'COMUNAS - HOME DELIVERY 2025'!$Q$7 -> 25306.704 | I364: =+'COMUNAS - HOME DELIVERY 2025'!I364*'COMUNAS - HOME DELIVERY 2025'!$Q$7 -> 27363.996 | J364: =+'COMUNAS - HOME DELIVERY 2025'!J364*'COMUNAS - HOME DELIVERY 2025'!$Q$7 -> 31018.824 | K364: =+'COMUNAS - HOME DELIVERY 2025'!K364*'COMUNAS - HOME DELIVERY 2025'!$Q$7 -> 35989.452 | L364: =+'COMUNAS - HOME DELIVERY 2025'!L364*'COMUNAS - HOME DELIVERY 2025'!$Q$7 -> 39956.976 | M364: =+'COMUNAS - HOME DELIVERY 2025'!M364*'COMUNAS - HOME DELIVERY 2025'!$Q$7 -> 1041.804 | N364: =+'COMUNAS - HOME DELIVERY 2025'!N364*'COMUNAS - HOME DELIVERY 2025'!$Q$7 -> 865.332
C365: TARAPACA (I) | D365: HRA | E365: HUARA | F365: =+'COMUNAS - HOME DELIVERY 2025'!F365*'COMUNAS - HOME DELIVERY 2025'!$Q$7 -> 8193.564 | G365: =+'COMUNAS - HOME DELIVERY 2025'!G365*'COMUNAS - HOME DELIVERY 2025'!$Q$7 -> 8936.604 | H365: =+'COMUNAS - HOME DELIVERY 2025'!H365*'COMUNAS - HOME DELIVERY 2025'!$Q$7 -> 9826.704 | I365: =+'COMUNAS - HOME DELIVERY 2025'!I365*'COMUNAS - HOME DELIVERY 2025'!$Q$7 -> 11883.996 | J365: =+'COMUNAS - HOME DELIVERY 2025'!J365*'COMUNAS - HOME DELIVERY 2025'!$Q$7 -> 15538.824 | K365: =+'COMUNAS - HOME DELIVERY 2025'!K365*'COMUNAS - HOME DELIVERY 2025'!$Q$7 -> 20509.452 | L365: =+'COMUNAS - HOME DELIVERY 2025'!L365*'COMUNAS - HOME DELIVERY 2025'!$Q$7 -> 24476.976 | M365: =+'COMUNAS - HOME DELIVERY 2025'!M365*'COMUNAS - HOME DELIVERY 2025'!$Q$7 -> 1041.804 | N365: =+'COMUNAS - HOME DELIVERY 2025'!N365*'COMUNAS - HOME DELIVERY 2025'!$Q$7 -> 865.332
C366: TARAPACA (I) | D366: OPC | E366: PICA | F366: =+'COMUNAS - HOME DELIVERY 2025'!F366*'COMUNAS - HOME DELIVERY 2025'!$Q$7 -> 8193.564 | G366: =+'COMUNAS - HOME DELIVERY 2025'!G366*'COMUNAS - HOME DELIVERY 2025'!$Q$7 -> 8936.604 | H366: =+'COMUNAS - HOME DELIVERY 2025'!H366*'COMUNAS - HOME DELIVERY 2025'!$Q$7 -> 9826.704 | I366: =+'COMUNAS - HOME DELIVERY 2025'!I366*'COMUNAS - HOME DELIVERY 2025'!$Q$7 -> 11883.996 | J366: =+'COMUNAS - HOME DELIVERY 2025'!J366*'COMUNAS - HOME DELIVERY 2025'!$Q$7 -> 15538.824 | K366: =+'COMUNAS - HOME DELIVERY 2025'!K366*'COMUNAS - HOME DELIVERY 2025'!$Q$7 -> 20509.452 | L366: =+'COMUNAS - HOME DELIVERY 2025'!L366*'COMUNAS - HOME DELIVERY 2025'!$Q$7 -> 24476.976 | M366: =+'COMUNAS - HOME DELIVERY 2025'!M366*'COMUNAS - HOME DELIVERY 2025'!$Q$7 -> 1041.804 | N366: =+'COMUNAS - HOME DELIVERY 2025'!N366*'COMUNAS - HOME DELIVERY 2025'!$Q$7 -> 865.332
C367: TARAPACA (I) | D367: PAM | E367: POZO ALMONTE | F367: =+'COMUNAS - HOME DELIVERY 2025'!F367*'COMUNAS - HOME DELIVERY 2025'!$Q$7 -> 8193.564 | G367: =+'COMUNAS - HOME DELIVERY 2025'!G367*'COMUNAS - HOME DELIVERY 2025'!$Q$7 -> 8936.604 | H367: =+'COMUNAS - HOME DELIVERY 2025'!H367*'COMUNAS - HOME DELIVERY 2025'!$Q$7 -> 9826.704 | I367: =+'COMUNAS - HOME DELIVERY 2025'!I367*'COMUNAS - HOME DELIVERY 2025'!$Q$7 -> 11883.996 | J367: =+'COMUNAS - HOME DELIVERY 2025'!J367*'COMUNAS - HOME DELIVERY 2025'!$Q$7 -> 15538.824 | K367: =+'COMUNAS - HOME DELIVERY 2025'!K367*'COMUNAS - HOME DELIVERY 2025'!$Q$7 -> 20509.452 | L367: =+'COMUNAS - HOME DELIVERY 2025'!L367*'COMUNAS - HOME DELIVERY 2025'!$Q$7 -> 24476.976 | M367: =+'COMUNAS - HOME DELIVERY 2025'!M367*'COMUNAS - HOME DELIVERY 2025'!$Q$7 -> 1041.804 | N367: =+'COMUNAS - HOME DELIVERY 2025'!N367*'COMUNAS - HOME DELIVERY 2025'!$Q$7 -> 865.332
C368: ANTOFAGASTA (II) | D368: ANF | E368: ANTOFAGASTA | F368: =+'COMUNAS - HOME DELIVERY 2025'!F368*'COMUNAS - HOME DELIVERY 2025'!$Q$7 -> 5243.592 | G368: =+'COMUNAS - HOME DELIVERY 2025'!G368*'COMUNAS - HOME DELIVERY 2025'!$Q$7 -> 5605.824 | H368: =+'COMUNAS - HOME DELIVERY 2025'!H368*'COMUNAS - HOME DELIVERY 2025'!$Q$7 -> 6162.072 | I368: =+'COMUNAS - HOME DELIVERY 2025'!I368*'COMUNAS - HOME DELIVERY 2025'!$Q$7 -> 7451.04 | J368: =+'COMUNAS - HOME DELIVERY 2025'!J368*'COMUNAS - HOME DELIVERY 2025'!$Q$7 -> 9277.68 | K368: =+'COMUNAS - HOME DELIVERY 2025'!K368*'COMUNAS - HOME DELIVERY 2025'!$Q$7 -> 12246.744 | L368: =+'COMUNAS - HOME DELIVERY 2025'!L368*'COMUNAS - HOME DELIVERY 2025'!$Q$7 -> 14690.52 | M368: =+'COMUNAS - HOME DELIVERY 2025'!M368*'COMUNAS - HOME DELIVERY 2025'!$Q$7 -> 663.576 | N368: =+'COMUNAS - HOME DELIVERY 2025'!N368*'COMUNAS - HOME DELIVERY 2025'!$Q$7 -> 546.96
... C397: MAGALLANES (XII) | D397: ATC | E397: ANTARTICA | F397: =+'COMUNAS - HOME DELIVERY 2025'!F397*'COMUNAS - HOME DELIVERY 2025'!$Q$7 -> 24679.764 | G397: =+'COMUNAS - HOME DELIVERY 2025'!G397*'COMUNAS - HOME DELIVERY 2025'!$Q$7 -> 25744.788 | H397: =+'COMUNAS - HOME DELIVERY 2025'!H397*'COMUNAS - HOME DELIVERY 2025'!$Q$7 -> 27103.932 | I397: =+'COMUNAS - HOME DELIVERY 2025'!I397*'COMUNAS - HOME DELIVERY 2025'!$Q$7 -> 29432.124 | J397: =+'COMUNAS - HOME DELIVERY 2025'!J397*'COMUNAS - HOME DELIVERY 2025'!$Q$7 -> 32834.628 | K397: =+'COMUNAS - HOME DELIVERY 2025'!K397*'COMUNAS - HOME DELIVERY 2025'!$Q$7 -> 38577.708 | L397: =+'COMUNAS - HOME DELIVERY 2025'!L397*'COMUNAS - HOME DELIVERY 2025'!$Q$7 -> 42902.82 | M397: =+'COMUNAS - HOME DELIVERY 2025'!M397*'COMUNAS - HOME DELIVERY 2025'!$Q$7 -> 1140.876 | N397: =+'COMUNAS - HOME DELIVERY 2025'!N397*'COMUNAS - HOME DELIVERY 2025'!$Q$7 -> 880.812
C399: Tarifa Servicio SAMEDAY
C400: REGION | E400: DESTINO | F400: 0 - 0.5 | G400: 0.5 - 1.5 | H400: 1.5 - 3 | I400: 3 - 6 | J400: 6 - 10 | K400: 10 - 16 | L400: 16 - 20 | M400: 20 - 50 * | N400: > 50 *
C401: REGION METROPOLITANA (XIII) | E401: SAMEDAY (RM) | F401: =+'COMUNAS - HOME DELIVERY 2025'!F401*'COMUNAS - HOME DELIVERY 2025'!$Q$7 -> 3328.2 | G401: =+'COMUNAS - HOME DELIVERY 2025'!G401*'COMUNAS - HOME DELIVERY 2025'!$Q$7 -> 3452.04 | H401: =+'COMUNAS - HOME DELIVERY 2025'!H401*'COMUNAS - HOME DELIVERY 2025'!$Q$7 -> 3674.952 | I401: =+'COMUNAS - HOME DELIVERY 2025'!I401*'COMUNAS - HOME DELIVERY 2025'!$Q$7 -> 4001.064 | J401: =+'COMUNAS - HOME DELIVERY 2025'!J401*'COMUNAS - HOME DELIVERY 2025'!$Q$7 -> 4633.68 | K401: =+'COMUNAS - HOME DELIVERY 2025'!K401*'COMUNAS - HOME DELIVERY 2025'!$Q$7 -> 5039.256 | L401: =+'COMUNAS - HOME DELIVERY 2025'!L401*'COMUNAS - HOME DELIVERY 2025'!$Q$7 -> 5898.912 | M401: =+'COMUNAS - HOME DELIVERY 2025'!M401*'COMUNAS - HOME DELIVERY 2025'!$Q$7 -> 465.432 | N401: =+'COMUNAS - HOME DELIVERY 2025'!N401*'COMUNAS - HOME DELIVERY 2025'!$Q$7 -> 465.432

Sheet COMUNAS - HOME DELIVERY 2026(2)
C2: PROPUESTA 2EBOX UM - HOME DELIVERY
C3: Tarifas Servicio EXPRESS - PRIORITY
C4: ORIGEN: SANTIAGO | F4: 1 | G4: 2 | H4: 3 | I4: 4 | J4: 5 | K4: 6 | L4: 7 | M4: 8 | N4: 9
C5: REGION | D5: POSTA | E5: COMUNA DESTINO | F5: 0 - 0.5 | G5: 0.5 - 1.5 | H5: 1.5 - 3 | I5: 3 - 6 | J5: 6 - 10 | K5: 10 - 16 | L5: 16 - 20 | M5: 20 - 50 * | N5: > 50 *
C6: METROPOLITANA (XIII) | D6: SCL | E6: SANTIAGO | F6: =+'COMUNAS - HOME DELIVERY 2026'!F6*1.1 -> 3328.4064 | G6: =+'COMUNAS - HOME DELIVERY 2026'!G6*1.1 -> 3452.1432 | H6: =+'COMUNAS - HOME DELIVERY 2026'!H6*1.1 -> 3674.6424 | I6: =+'COMUNAS - HOME DELIVERY 2026'!I6*1.1 -> 4000.4448 | J6: =+'COMUNAS - HOME DELIVERY 2026'!J6*1.1 -> 4632.7512 | K6: =+'COMUNAS - HOME DELIVERY 2026'!K6*1.1 -> 5039.1528 | L6: =+'COMUNAS - HOME DELIVERY 2026'!L6*1.1 -> 5899.6344 | M6: =+'COMUNAS - HOME DELIVERY 2026'!M6*1.1 -> 340.56 | N6: =+'COMUNAS - HOME DELIVERY 2026'!N6*1.1 -> 259.9608
C7: METROPOLITANA (XIII) | D7: RLT | E7: RECOLETA | F7: =+'COMUNAS - HOME DELIVERY 2026'!F7*1.1 -> 3328.4064 | G7: =+'COMUNAS - HOME DELIVERY 2026'!G7*1.1 -> 3452.1432 | H7: =+'COMUNAS - HOME DELIVERY 2026'!H7*1.1 -> 3674.6424 | I7: =+'COMUNAS - HOME DELIVERY 2026'!I7*1.1 -> 4000.4448 | J7: =+'COMUNAS - HOME DELIVERY 2026'!J7*1.1 -> 4632.7512 | K7: =+'COMUNAS - HOME DELIVERY 2026'!K7*1.1 -> 5039.1528 | L7: =+'COMUNAS - HOME DELIVERY 2026'!L7*1.1 -> 5899.6344 | M7: =+'COMUNAS - HOME DELIVERY 2026'!M7*1.1 -> 340.56 | N7: =+'COMUNAS - HOME DELIVERY 2026'!N7*1.1 -> 259.9608
C8: METROPOLITANA (XIII) | D8: IDP | E8: INDEPENDENCIA | F8: =+'COMUNAS - HOME DELIVERY 2026'!F8*1.1 -> 3328.4064 | G8: =+'COMUNAS - HOME DELIVERY 2026'!G8*1.1 -> 3452.1432 | H8: =+'COMUNAS - HOME DELIVERY 2026'!H8*1.1 -> 3674.6424 | I8: =+'COMUNAS - HOME DELIVERY 2026'!I8*1.1 -> 4000.4448 | J8: =+'COMUNAS - HOME DELIVERY 2026'!J8*1.1 -> 4632.7512 | K8: =+'COMUNAS - HOME DELIVERY 2026'!K8*1.1 -> 5039.1528 | L8: =+'COMUNAS - HOME DELIVERY 2026'!L8*1.1 -> 5899.6344 | M8: =+'COMUNAS - HOME DELIVERY 2026'!M8*1.1 -> 340.56 | N8: =+'COMUNAS - HOME DELIVERY 2026'!N8*1.1 -> 259.9608
C9: METROPOLITANA (XIII) | D9: QTN | E9: QUINTA NORMAL | F9: =+'COMUNAS - HOME DELIVERY 2026'!F9*1.1 -> 3328.4064 | G9: =+'COMUNAS - HOME DELIVERY 2026'!G9*1.1 -> 3452.1432 | H9: =+'COMUNAS - HOME DELIVERY 2026'!H9*1.1 -> 3674.6424 | I9: =+'COMUNAS - HOME DELIVERY 2026'!I9*1.1 -> 4000.4448 | J9: =+'COMUNAS - HOME DELIVERY 2026'!J9*1.1 -> 4632.7512 | K9: =+'COMUNAS - HOME DELIVERY 2026'!K9*1.1 -> 5039.1528 | L9: =+'COMUNAS - HOME DELIVERY 2026'!L9*1.1 -> 5899.6344 | M9: =+'COMUNAS - HOME DELIVERY 2026'!M9*1.1 -> 340.56 | N9: =+'COMUNAS - HOME DELIVERY 2026'!N9*1.1 -> 259.9608
C10: METROPOLITANA (XIII) | D10: MAI | E10: MAIPU | F10: =+'COMUNAS - HOME DELIVERY 2026'!F10*1.1 -> 3328.4064 | G10: =+'COMUNAS - HOME DELIVERY 2026'!G10*1.1 -> 3452.1432 | H10: =+'COMUNAS - HOME DELIVERY 2026'!H10*1.1 -> 3674.6424 | I10: =+'COMUNAS - HOME DELIVERY 2026'!I10*1.1 -> 4000.4448 | J10: =+'COMUNAS - HOME DELIVERY 2026'!J10*1.1 -> 4632.7512 | K10: =+'COMUNAS - HOME DELIVERY 2026'!K10*1.1 -> 5039.1528 | L10: =+'COMUNAS - HOME DELIVERY 2026'!L10*1.1 -> 5899.6344 | M10: =+'COMUNAS - HOME DELIVERY 2026'!M10*1.1 -> 340.56 | N10: =+'COMUNAS - HOME DELIVERY 2026'!N10*1.1 -> 259.9608
C11: METROPOLITANA (XIII) | D11: PUD | E11: PUDAHUEL | F11: =+'COMUNAS - HOME DELIVERY 2026'!F11*1.1 -> 3328.4064 | G11: =+'COMUNAS - HOME DELIVERY 2026'!G11*1.1 -> 3452.1432 | H11: =+'COMUNAS - HOME DELIVERY 2026'!H11*1.1 -> 3674.6424 | I11: =+'COMUNAS - HOME DELIVERY 2026'!I11*1.1 -> 4000.4448 | J11: =+'COMUNAS - HOME DELIVERY 2026'!J11*1.1 -> 4632.7512 | K11: =+'COMUNAS - HOME DELIVERY 2026'!K11*1.1 -> 5039.1528 | L11: =+'COMUNAS - HOME DELIVERY 2026'!L11*1.1 -> 5899.6344 | M11: =+'COMUNAS - HOME DELIVERY 2026'!M11*1.1 -> 340.56 | N11: =+'COMUNAS - HOME DELIVERY 2026'!N11*1.1 -> 259.9608
C12: METROPOLITANA (XIII) | D12: REN | E12: RENCA | F12: =+'COMUNAS - HOME DELIVERY 2026'!F12*1.1 -> 3328.4064 | G12: =+'COMUNAS - HOME DELIVERY 2026'!G12*1.1 -> 3452.1432 | H12: =+'COMUNAS - HOME DELIVERY 2026'!H12*1.1 -> 3674.6424 | I12: =+'COMUNAS - HOME DELIVERY 2026'!I12*1.1 -> 4000.4448 | J12: =+'COMUNAS - HOME DELIVERY 2026'!J12*1.1 -> 4632.7512 | K12: =+'COMUNAS - HOME DELIVERY 2026'!K12*1.1 -> 5039.1528 | L12: =+'COMUNAS - HOME DELIVERY 2026'!L12*1.1 -> 5899.6344 | M12: =+'COMUNAS - HOME DELIVERY 2026'!M12*1.1 -> 340.56 | N12: =+'COMUNAS - HOME DELIVERY 2026'!N12*1.1 -> 259.9608
C13: METROPOLITANA (XIII) | D13: QLC | E13: QUILICURA | F13: =+'COMUNAS - HOME DELIVERY 2026'!F13*1.1 -> 3328.4064 | G13: =+'COMUNAS - HOME DELIVERY 2026'!G13*1.1 -> 3452.1432 | H13: =+'COMUNAS - HOME DELIVERY 2026'!H13*1.1 -> 3674.6424 | I13: =+'COMUNAS - HOME DELIVERY 2026'!I13*1.1 -> 4000.4448 | J13: =+'COMUNAS - HOME DELIVERY 2026'!J13*1.1 -> 4632.7512 | K13: =+'COMUNAS - HOME DELIVERY 2026'!K13*1.1 -> 5039.1528 | L13: =+'COMUNAS - HOME DELIVERY 2026'!L13*1.1 -> 5899.6344 | M13: =+'COMUNAS - HOME DELIVERY 2026'!M13*1.1 -> 340.56 | N13: =+'COMUNAS - HOME DELIVERY 2026'!N13*1.1 -> 259.9608
C14: METROPOLITANA (XIII) | D14: CNH | E14: CONCHALI | F14: =+'COMUNAS - HOME DELIVERY 2026'!F14*1.1 -> 3328.4064 | G14: =+'COMUNAS - HOME DELIVERY 2026'!G14*1.1 -> 3452.1432 | H14: =+'COMUNAS - HOME DELIVERY 2026'!H14*1.1 -> 3674.6424 | I14: =+'COMUNAS - HOME DELIVERY 2026'!I14*1.1 -> 4000.4448 | J14: =+'COMUNAS - HOME DELIVERY 2026'!J14*1.1 -> 4632.7512 | K14: =+'COMUNAS - HOME DELIVERY 2026'!K14*1.1 -> 5039.1528 | L14: =+'COMUNAS - HOME DELIVERY 2026'!L14*1.1 -> 5899.6344 | M14: =+'COMUNAS - HOME DELIVERY 2026'!M14*1.1 -> 340.56 | N14: =+'COMUNAS - HOME DELIVERY 2026'!N14*1.1 -> 259.9608
C15: METROPOLITANA (XIII) | D15: LPR | E15: LO PRADO | F15: =+'COMUNAS - HOME DELIVERY 2026'!F15*1.1 -> 3328.4064 | G15: =+'COMUNAS - HOME DELIVERY 2026'!G15*1.1 -> 3452.1432 | H15: =+'COMUNAS - HOME DELIVERY 2026'!H15*1.1 -> 3674.6424 | I15: =+'COMUNAS - HOME DELIVERY 2026'!I15*1.1 -> 4000.4448 | J15: =+'COMUNAS - HOME DELIVERY 2026'!J15*1.1 -> 4632.7512 | K15: =+'COMUNAS - HOME DELIVERY 2026'!K15*1.1 -> 5039.1528 | L15: =+'COMUNAS - HOME DELIVERY 2026'!L15*1.1 -> 5899.6344 | M15: =+'COMUNAS - HOME DELIVERY 2026'!M15*1.1 -> 340.56 | N15: =+'COMUNAS - HOME DELIVERY 2026'!N15*1.1 -> 259.9608
C16: METROPOLITANA (XIII) | D16: CNV | E16: CERRO NAVIA | F16: =+'COMUNAS - HOME DELIVERY 2026'!F16*1.1 -> 3328.4064 | G16: =+'COMUNAS - HOME DELIVERY 2026'!G16*1.1 -> 3452.1432 | H16: =+'COMUNAS - HOME DELIVERY 2026'!H16*1.1 -> 3674.6424 | I16: =+'COMUNAS - HOME DELIVERY 2026'!I16*1.1 -> 4000.4448 | J16: =+'COMUNAS - HOME DELIVERY 2026'!J16*1.1 -> 4632.7512 | K16: =+'COMUNAS - HOME DELIVERY 2026'!K16*1.1 -> 5039.1528 | L16: =+'COMUNAS - HOME DELIVERY 2026'!L16*1.1 -> 5899.6344 | M16: =+'COMUNAS - HOME DELIVERY 2026'!M16*1.1 -> 340.56 | N16: =+'COMUNAS - HOME DELIVERY 2026'!N16*1.1 -> 259.9608
C17: METROPOLITANA (XIII) | D17: ECE | E17: ESTACION CENTRAL | F17: =+'COMUNAS - HOME DELIVERY 2026'!F17*1.1 -> 3328.4064 | G17: =+'COMUNAS - HOME DELIVERY 2026'!G17*1.1 -> 3452.1432 | H17: =+'COMUNAS - HOME DELIVERY 2026'!H17*1.1 -> 3674.6424 | I17: =+'COMUNAS - HOME DELIVERY 2026'!I17*1.1 -> 4000.4448 | J17: =+'COMUNAS - HOME DELIVERY 2026'!J17*1.1 -> 4632.7512 | K17: =+'COMUNAS - HOME DELIVERY 2026'!K17*1.1 -> 5039.1528 | L17: =+'COMUNAS - HOME DELIVERY 2026'!L17*1.1 -> 5899.6344 | M17: =+'COMUNAS - HOME DELIVERY 2026'!M17*1.1 -> 340.56 | N17: =+'COMUNAS - HOME DELIVERY 2026'!N17*1.1 -> 259.9608
... C310: LOS LAGOS (X) | D310: SPL | E310: SAN PABLO | F310: =+'COMUNAS - HOME DELIVERY 2026'!F310*1.1 -> 5626.0512 | G310: =+'COMUNAS - HOME DELIVERY 2026'!G310*1.1 -> 6006.3432 | H310: =+'COMUNAS - HOME DELIVERY 2026'!H310*1.1 -> 6655.6776 | I310: =+'COMUNAS - HOME DELIVERY 2026'!I310*1.1 -> 7366.3128 | J310: =+'COMUNAS - HOME DELIVERY 2026'!J310*1.1 -> 9368.8056 | K310: =+'COMUNAS - HOME DELIVERY 2026'!K310*1.1 -> 10691.314 | L310: =+'COMUNAS - HOME DELIVERY 2026'!L310*1.1 -> 12079.663 | M310: =+'COMUNAS - HOME DELIVERY 2026'!M310*1.1 -> 635.712 | N310: =+'COMUNAS - HOME DELIVERY 2026'!N310*1.1 -> 529.0032
C311: Extremos Aéreos - Tarifas Servicio PRIORITY
C312: REGION | D312: POSTA | E312: COMUNA DESTINO | F312: 0 - 0.5 | G312: 0.5 - 1.5 | H312: 1.5 - 3 | I312: 3 - 6 | J312: 6 - 10 | K312: 10 - 16 | L312: 16 - 20 | M312: 20 - 50 * | N312: > 50 *
C313: ARICA Y PARINACOTA (XV) | D313: ARI | E313: ARICA | F313: =+'COMUNAS - HOME DELIVERY 2026'!F313*1.1 -> 6923.5848 | G313: =+'COMUNAS - HOME DELIVERY 2026'!G313*1.1 -> 8160.9528 | H313: =+'COMUNAS - HOME DELIVERY 2026'!H313*1.1 -> 9879.6456 | I313: =+'COMUNAS - HOME DELIVERY 2026'!I313*1.1 -> 11685.749 | J313: =+'COMUNAS - HOME DELIVERY 2026'!J313*1.1 -> 19485.708 | K313: =+'COMUNAS - HOME DELIVERY 2026'!K313*1.1 -> 30574.342 | L313: =+'COMUNAS - HOME DELIVERY 2026'!L313*1.1 -> 35847.346 | M313: =+'COMUNAS - HOME DELIVERY 2026'!M313*1.1 -> 1769.7768 | N313: =+'COMUNAS - HOME DELIVERY 2026'!N313*1.1 -> 1708.476
C314: ARICA Y PARINACOTA (XV) | D314: CAM | E314: CAMARONES | F314: =+'COMUNAS - HOME DELIVERY 2026'!F314*1.1 -> 27413.377 | G314: =+'COMUNAS - HOME DELIVERY 2026'!G314*1.1 -> 29269.429 | H314: =+'COMUNAS - HOME DELIVERY 2026'!H314*1.1 -> 31847.468 | I314: =+'COMUNAS - HOME DELIVERY 2026'!I314*1.1 -> 34556.623 | J314: =+'COMUNAS - HOME DELIVERY 2026'!J314*1.1 -> 46256.562 | K314: =+'COMUNAS - HOME DELIVERY 2026'!K314*1.1 -> 62889.512 | L314: =+'COMUNAS - HOME DELIVERY 2026'!L314*1.1 -> 70799.018 | M314: =+'COMUNAS - HOME DELIVERY 2026'!M314*1.1 -> 2654.6652 | N314: =+'COMUNAS - HOME DELIVERY 2026'!N314*1.1 -> 2562.714
C315: ARICA Y PARINACOTA (XV) | D315: LGR | E315: GENERAL LAGOS | F315: =+'COMUNAS - HOME DELIVERY 2026'!F315*1.1 -> 27413.377 | G315: =+'COMUNAS - HOME DELIVERY 2026'!G315*1.1 -> 29269.429 | H315: =+'COMUNAS - HOME DELIVERY 2026'!H315*1.1 -> 31847.468 | I315: =+'COMUNAS - HOME DELIVERY 2026'!I315*1.1 -> 34556.623 | J315: =+'COMUNAS - HOME DELIVERY 2026'!J315*1.1 -> 46256.562 | K315: =+'COMUNAS - HOME DELIVERY 2026'!K315*1.1 -> 62889.512 | L315: =+'COMUNAS - HOME DELIVERY 2026'!L315*1.1 -> 70799.018 | M315: =+'COMUNAS - HOME DELIVERY 2026'!M315*1.1 -> 2654.6652 | N315: =+'COMUNAS - HOME DELIVERY 2026'!N315*1.1 -> 2562.714
C316: ARICA Y PARINACOTA (XV) | D316: PTR | E316: PUTRE | F316: =+'COMUNAS - HOME DELIVERY 2026'!F316*1.1 -> 27413.377 | G316: =+'COMUNAS - HOME DELIVERY 2026'!G316*1.1 -> 29269.429 | H316: =+'COMUNAS - HOME DELIVERY 2026'!H316*1.1 -> 31847.468 | I316: =+'COMUNAS - HOME DELIVERY 2026'!I316*1.1 -> 34556.623 | J316: =+'COMUNAS - HOME DELIVERY 2026'!J316*1.1 -> 46256.562 | K316: =+'COMUNAS - HOME DELIVERY 2026'!K316*1.1 -> 62889.512 | L316: =+'COMUNAS - HOME DELIVERY 2026'!L316*1.1 -> 70799.018 | M316: =+'COMUNAS - HOME DELIVERY 2026'!M316*1.1 -> 2654.6652 | N316: =+'COMUNAS - HOME DELIVERY 2026'!N316*1.1 -> 2562.714
C317: TARAPACA (I) | D317: IQQ | E317: IQUIQUE | F317: =+'COMUNAS - HOME DELIVERY 2026'!F317*1.1 -> 6471.7752 | G317: =+'COMUNAS - HOME DELIVERY 2026'!G317*1.1 -> 7627.4088 | H317: =+'COMUNAS - HOME DELIVERY 2026'!H317*1.1 -> 9234.852 | I317: =+'COMUNAS - HOME DELIVERY 2026'!I317*1.1 -> 10920.624 | J317: =+'COMUNAS - HOME DELIVERY 2026'!J317*1.1 -> 18209.743 | K317: =+'COMUNAS - HOME DELIVERY 2026'!K317*1.1 -> 28577.525 | L317: =+'COMUNAS - HOME DELIVERY 2026'!L317*1.1 -> 33729.062 | M317: =+'COMUNAS - HOME DELIVERY 2026'!M317*1.1 -> 1716.4224 | N317: =+'COMUNAS - HOME DELIVERY 2026'!N317*1.1 -> 1614.2544
C318: TARAPACA (I) | D318: AHP | E318: ALTO HOSPICIO | F318: =+'COMUNAS - HOME DELIVERY 2026'!F318*1.1 -> 6471.7752 | G318: =+'COMUNAS - HOME DELIVERY 2026'!G318*1.1 -> 7627.4088 | H318: =+'COMUNAS - HOME DELIVERY 2026'!H318*1.1 -> 9234.852 | I318: =+'COMUNAS - HOME DELIVERY 2026'!I318*1.1 -> 10920.624 | J318: =+'COMUNAS - HOME DELIVERY 2026'!J318*1.1 -> 18209.743 | K318: =+'COMUNAS - HOME DELIVERY 2026'!K318*1.1 -> 28577.525 | L318: =+'COMUNAS - HOME DELIVERY 2026'!L318*1.1 -> 33729.062 | M318: =+'COMUNAS - HOME DELIVERY 2026'!M318*1.1 -> 1716.4224 | N318: =+'COMUNAS - HOME DELIVERY 2026'!N318*1.1 -> 1614.2544
C319: TARAPACA (I) | D319: CMN | E319: CAMINA | F319: =+'COMUNAS - HOME DELIVERY 2026'!F319*1.1 -> 26735.663 | G319: =+'COMUNAS - HOME DELIVERY 2026'!G319*1.1 -> 28469.113 | H319: =+'COMUNAS - HOME DELIVERY 2026'!H319*1.1 -> 30880.278 | I319: =+'COMUNAS - HOME DELIVERY 2026'!I319*1.1 -> 33408.936 | J319: =+'COMUNAS - HOME DELIVERY 2026'!J319*1.1 -> 44342.615 | K319: =+'COMUNAS - HOME DELIVERY 2026'!K319*1.1 -> 59894.287 | L319: =+'COMUNAS - HOME DELIVERY 2026'!L319*1.1 -> 67621.594 | M319: =+'COMUNAS - HOME DELIVERY 2026'!M319*1.1 -> 2574.6336 | N319: =+'COMUNAS - HOME DELIVERY 2026'!N319*1.1 -> 2421.3816
C320: TARAPACA (I) | D320: COE | E320: COLCHANE | F320: =+'COMUNAS - HOME DELIVERY 2026'!F320*1.1 -> 26735.663 | G320: =+'COMUNAS - HOME DELIVERY 2026'!G320*1.1 -> 28469.113 | H320: =+'COMUNAS - HOME DELIVERY 2026'!H320*1.1 -> 30880.278 | I320: =+'COMUNAS - HOME DELIVERY 2026'!I320*1.1 -> 33408.936 | J320: =+'COMUNAS - HOME DELIVERY 2026'!J320*1.1 -> 44342.615 | K320: =+'COMUNAS - HOME DELIVERY 2026'!K320*1.1 -> 59894.287 | L320: =+'COMUNAS - HOME DELIVERY 2026'!L320*1.1 -> 67621.594 | M320: =+'COMUNAS - HOME DELIVERY 2026'!M320*1.1 -> 2574.6336 | N320: =+'COMUNAS - HOME DELIVERY 2026'!N320*1.1 -> 2421.3816
C321: TARAPACA (I) | D321: HRA | E321: HUARA | F321: =+'COMUNAS - HOME DELIVERY 2026'!F321*1.1 -> 9707.6628 | G321: =+'COMUNAS - HOME DELIVERY 2026'!G321*1.1 -> 11441.113 | H321: =+'COMUNAS - HOME DELIVERY 2026'!H321*1.1 -> 13852.278 | I321: =+'COMUNAS - HOME DELIVERY 2026'!I321*1.1 -> 16380.936 | J321: =+'COMUNAS - HOME DELIVERY 2026'!J321*1.1 -> 27314.615 | K321: =+'COMUNAS - HOME DELIVERY 2026'!K321*1.1 -> 42866.287 | L321: =+'COMUNAS - HOME DELIVERY 2026'!L321*1.1 -> 50593.594 | M321: =+'COMUNAS - HOME DELIVERY 2026'!M321*1.1 -> 2574.6336 | N321: =+'COMUNAS - HOME DELIVERY 2026'!N321*1.1 -> 2421.3816
C322: TARAPACA (I) | D322: OPC | E322: PICA | F322: =+'COMUNAS - HOME DELIVERY 2026'!F322*1.1 -> 9707.6628 | G322: =+'COMUNAS - HOME DELIVERY 2026'!G322*1.1 -> 11441.113 | H322: =+'COMUNAS - HOME DELIVERY 2026'!H322*1.1 -> 13852.278 | I322: =+'COMUNAS - HOME DELIVERY 2026'!I322*1.1 -> 16380.936 | J322: =+'COMUNAS - HOME DELIVERY 2026'!J322*1.1 -> 27314.615 | K322: =+'COMUNAS - HOME DELIVERY 2026'!K322*1.1 -> 42866.287 | L322: =+'COMUNAS - HOME DELIVERY 2026'!L322*1.1 -> 50593.594 | M322: =+'COMUNAS - HOME DELIVERY 2026'!M322*1.1 -> 2574.6336 | N322: =+'COMUNAS - HOME DELIVERY 2026'!N322*1.1 -> 2421.3816
C323: TARAPACA (I) | D323: PAM | E323: POZO ALMONTE | F323: =+'COMUNAS - HOME DELIVERY 2026'!F323*1.1 -> 9707.6628 | G323: =+'COMUNAS - HOME DELIVERY 2026'!G323*1.1 -> 11441.113 | H323: =+'COMUNAS - HOME DELIVERY 2026'!H323*1.1 -> 13852.278 | I323: =+'COMUNAS - HOME DELIVERY 2026'!I323*1.1 -> 16380.936 | J323: =+'COMUNAS - HOME DELIVERY 2026'!J323*1.1 -> 27314.615 | K323: =+'COMUNAS - HOME DELIVERY 2026'!K323*1.1 -> 42866.287 | L323: =+'COMUNAS - HOME DELIVERY 2026'!L323*1.1 -> 50593.594 | M323: =+'COMUNAS - HOME DELIVERY 2026'!M323*1.1 -> 2574.6336 | N323: =+'COMUNAS - HOME DELIVERY 2026'!N323*1.1 -> 2421.3816
C324: ANTOFAGASTA (II) | D324: ANF | E324: ANTOFAGASTA | F324: =+'COMUNAS - HOME DELIVERY 2026'!F324*1.1 -> 6262.8984 | G324: =+'COMUNAS - HOME DELIVERY 2026'!G324*1.1 -> 7243.7112 | H324: =+'COMUNAS - HOME DELIVERY 2026'!H324*1.1 -> 8772.8256 | I324: =+'COMUNAS - HOME DELIVERY 2026'!I324*1.1 -> 10374.593 | J324: =+'COMUNAS - HOME DELIVERY 2026'!J324*1.1 -> 17300.448 | K324: =+'COMUNAS - HOME DELIVERY 2026'!K324*1.1 -> 27147.173 | L324: =+'COMUNAS - HOME DELIVERY 2026'!L324*1.1 -> 32121.619 | M324: =+'COMUNAS - HOME DELIVERY 2026'!M324*1.1 -> 1638.0936 | N324: =+'COMUNAS - HOME DELIVERY 2026'!N324*1.1 -> 1527.9792
... C353: MAGALLANES (XII) | D353: ATC | E353: ANTARTICA | F353: =+'COMUNAS - HOME DELIVERY 2026'!F353*1.1 -> 27583.657 | G353: =+'COMUNAS - HOME DELIVERY 2026'!G353*1.1 -> 29375.003 | H353: =+'COMUNAS - HOME DELIVERY 2026'!H353*1.1 -> 31968.367 | I353: =+'COMUNAS - HOME DELIVERY 2026'!I353*1.1 -> 34025.35 | J353: =+'COMUNAS - HOME DELIVERY 2026'!J353*1.1 -> 45999.439 | K353: =+'COMUNAS - HOME DELIVERY 2026'!K353*1.1 -> 65046.96 | L353: =+'COMUNAS - HOME DELIVERY 2026'!L353*1.1 -> 73576.285 | M353: =+'COMUNAS - HOME DELIVERY 2026'!M353*1.1 -> 2925.4104 | N353: =+'COMUNAS - HOME DELIVERY 2026'!N353*1.1 -> 2758.536
C355: Extremos Terrestre - Tarifas Servicio EXPRESS
C356: REGION | D356: POSTA | E356: COMUNA DESTINO | F356: 0 - 0.5 | G356: 0.5 - 1.5 | H356: 1.5 - 3 | I356: 3 - 6 | J356: 6 - 10 | K356: 10 - 16 | L356: 16 - 20 | M356: 20 - 50 * | N356: > 50 *
C357: ARICA Y PARINACOTA (XV) | D357: ARI | E357: ARICA | F357: =+'COMUNAS - HOME DELIVERY 2026'!F357*1.1 -> 6299.2248 | G357: =+'COMUNAS - HOME DELIVERY 2026'!G357*1.1 -> 7013.2656 | H357: =+'COMUNAS - HOME DELIVERY 2026'!H357*1.1 -> 7710.2784 | I357: =+'COMUNAS - HOME DELIVERY 2026'!I357*1.1 -> 9323.3976 | J357: =+'COMUNAS - HOME DELIVERY 2026'!J357*1.1 -> 12192.048 | K357: =+'COMUNAS - HOME DELIVERY 2026'!K357*1.1 -> 16092.595 | L357: =+'COMUNAS - HOME DELIVERY 2026'!L357*1.1 -> 19100.875 | M357: =+'COMUNAS - HOME DELIVERY 2026'!M357*1.1 -> 777.612 | N357: =+'COMUNAS - HOME DELIVERY 2026'!N357*1.1 -> 664.092
C358: ARICA Y PARINACOTA (XV) | D358: CAM | E358: CAMARONES | F358: =+'COMUNAS - HOME DELIVERY 2026'!F358*1.1 -> 26476.837 | G358: =+'COMUNAS - HOME DELIVERY 2026'!G358*1.1 -> 27547.898 | H358: =+'COMUNAS - HOME DELIVERY 2026'!H358*1.1 -> 28593.418 | I358: =+'COMUNAS - HOME DELIVERY 2026'!I358*1.1 -> 31013.096 | J358: =+'COMUNAS - HOME DELIVERY 2026'!J358*1.1 -> 35316.072 | K358: =+'COMUNAS - HOME DELIVERY 2026'!K358*1.1 -> 41166.893 | L358: =+'COMUNAS - HOME DELIVERY 2026'!L358*1.1 -> 45679.313 | M358: =+'COMUNAS - HOME DELIVERY 2026'!M358*1.1 -> 1166.418 | N358: =+'COMUNAS - HOME DELIVERY 2026'!N358*1.1 -> 996.138
C359: ARICA Y PARINACOTA (XV) | D359: LGR | E359: GENERAL LAGOS | F359: =+'COMUNAS - HOME DELIVERY 2026'!F359*1.1 -> 26476.837 | G359: =+'COMUNAS - HOME DELIVERY 2026'!G359*1.1 -> 27547.898 | H359: =+'COMUNAS - HOME DELIVERY 2026'!H359*1.1 -> 28593.418 | I359: =+'COMUNAS - HOME DELIVERY 2026'!I359*1.1 -> 31013.096 | J359: =+'COMUNAS - HOME DELIVERY 2026'!J359*1.1 -> 35316.072 | K359: =+'COMUNAS - HOME DELIVERY 2026'!K359*1.1 -> 41166.893 | L359: =+'COMUNAS - HOME DELIVERY 2026'!L359*1.1 -> 45679.313 | M359: =+'COMUNAS - HOME DELIVERY 2026'!M359*1.1 -> 1166.418 | N359: =+'COMUNAS - HOME DELIVERY 2026'!N359*1.1 -> 996.138
C360: ARICA Y PARINACOTA (XV) | D360: PTR | E360: PUTRE | F360: =+'COMUNAS - HOME DELIVERY 2026'!F360*1.1 -> 26476.837 | G360: =+'COMUNAS - HOME DELIVERY 2026'!G360*1.1 -> 27547.898 | H360: =+'COMUNAS - HOME DELIVERY 2026'!H360*1.1 -> 28593.418 | I360: =+'COMUNAS - HOME DELIVERY 2026'!I360*1.1 -> 31013.096 | J360: =+'COMUNAS - HOME DELIVERY 2026'!J360*1.1 -> 35316.072 | K360: =+'COMUNAS - HOME DELIVERY 2026'!K360*1.1 -> 41166.893 | L360: =+'COMUNAS - HOME DELIVERY 2026'!L360*1.1 -> 45679.313 | M360: =+'COMUNAS - HOME DELIVERY 2026'!M360*1.1 -> 1166.418 | N360: =+'COMUNAS - HOME DELIVERY 2026'!N360*1.1 -> 996.138
C361: TARAPACA (I) | D361: IQQ | E361: IQUIQUE | F361: =+'COMUNAS - HOME DELIVERY 2026'!F361*1.1 -> 6008.6136 | G361: =+'COMUNAS - HOME DELIVERY 2026'!G361*1.1 -> 6553.5096 | H361: =+'COMUNAS - HOME DELIVERY 2026'!H361*1.1 -> 7206.2496 | I361: =+'COMUNAS - HOME DELIVERY 2026'!I361*1.1 -> 8714.9304 | J361: =+'COMUNAS - HOME DELIVERY 2026'!J361*1.1 -> 11395.138 | K361: =+'COMUNAS - HOME DELIVERY 2026'!K361*1.1 -> 15040.265 | L361: =+'COMUNAS - HOME DELIVERY 2026'!L361*1.1 -> 17949.782 | M361: =+'COMUNAS - HOME DELIVERY 2026'!M361*1.1 -> 763.9896 | N361: =+'COMUNAS - HOME DELIVERY 2026'!N361*1.1 -> 634.5768
C362: TARAPACA (I) | D362: AHP | E362: ALTO HOSPICIO | F362: =+'COMUNAS - HOME DELIVERY 2026'!F362*1.1 -> 6008.6136 | G362: =+'COMUNAS - HOME DELIVERY 2026'!G362*1.1 -> 6553.5096 | H362: =+'COMUNAS - HOME DELIVERY 2026'!H362*1.1 -> 7206.2496 | I362: =+'COMUNAS - HOME DELIVERY 2026'!I362*1.1 -> 8714.9304 | J362: =+'COMUNAS - HOME DELIVERY 2026'!J362*1.1 -> 11395.138 | K362: =+'COMUNAS - HOME DELIVERY 2026'!K362*1.1 -> 15040.265 | L362: =+'COMUNAS - HOME DELIVERY 2026'!L362*1.1 -> 17949.782 | M362: =+'COMUNAS - HOME DELIVERY 2026'!M362*1.1 -> 763.9896 | N362: =+'COMUNAS - HOME DELIVERY 2026'!N362*1.1 -> 634.5768
C363: TARAPACA (I) | D363: CMN | E363: CAMINA | F363: =+'COMUNAS - HOME DELIVERY 2026'!F363*1.1 -> 26040.92 | G363: =+'COMUNAS - HOME DELIVERY 2026'!G363*1.1 -> 26858.264 | H363: =+'COMUNAS - HOME DELIVERY 2026'!H363*1.1 -> 27837.374 | I363: =+'COMUNAS - HOME DELIVERY 2026'!I363*1.1 -> 30100.396 | J363: =+'COMUNAS - HOME DELIVERY 2026'!J363*1.1 -> 34120.706 | K363: =+'COMUNAS - HOME DELIVERY 2026'!K363*1.1 -> 39588.397 | L363: =+'COMUNAS - HOME DELIVERY 2026'!L363*1.1 -> 43952.674 | M363: =+'COMUNAS - HOME DELIVERY 2026'!M363*1.1 -> 1145.9844 | N363: =+'COMUNAS - HOME DELIVERY 2026'!N363*1.1 -> 951.8652
C364: TARAPACA (I) | D364: COE | E364: COLCHANE | F364: =+'COMUNAS - HOME DELIVERY 2026'!F364*1.1 -> 26040.92 | G364: =+'COMUNAS - HOME DELIVERY 2026'!G364*1.1 -> 26858.264 | H364: =+'COMUNAS - HOME DELIVERY 2026'!H364*1.1 -> 27837.374 | I364: =+'COMUNAS - HOME DELIVERY 2026'!I364*1.1 -> 30100.396 | J364: =+'COMUNAS - HOME DELIVERY 2026'!J364*1.1 -> 34120.706 | K364: =+'COMUNAS - HOME DELIVERY 2026'!K364*1.1 -> 39588.397 | L364: =+'COMUNAS - HOME DELIVERY 2026'!L364*1.1 -> 43952.674 | M364: =+'COMUNAS - HOME DELIVERY 2026'!M364*1.1 -> 1145.9844 | N364: =+'COMUNAS - HOME DELIVERY 2026'!N364*1.1 -> 951.8652
C365: TARAPACA (I) | D365: HRA | E365: HUARA | F365: =+'COMUNAS - HOME DELIVERY 2026'!F365*1.1 -> 9012.9204 | G365: =+'COMUNAS - HOME DELIVERY 2026'!G365*1.1 -> 9830.2644 | H365: =+'COMUNAS - HOME DELIVERY 2026'!H365*1.1 -> 10809.374 | I365: =+'COMUNAS - HOME DELIVERY 2026'!I365*1.1 -> 13072.396 | J365: =+'COMUNAS - HOME DELIVERY 2026'!J365*1.1 -> 17092.706 | K365: =+'COMUNAS - HOME DELIVERY 2026'!K365*1.1 -> 22560.397 | L365: =+'COMUNAS - HOME DELIVERY 2026'!L365*1.1 -> 26924.674 | M365: =+'COMUNAS - HOME DELIVERY 2026'!M365*1.1 -> 1145.9844 | N365: =+'COMUNAS - HOME DELIVERY 2026'!N365*1.1 -> 951.8652
C366: TARAPACA (I) | D366: OPC | E366: PICA | F366: =+'COMUNAS - HOME DELIVERY 2026'!F366*1.1 -> 9012.9204 | G366: =+'COMUNAS - HOME DELIVERY 2026'!G366*1.1 -> 9830.2644 | H366: =+'COMUNAS - HOME DELIVERY 2026'!H366*1.1 -> 10809.374 | I366: =+'COMUNAS - HOME DELIVERY 2026'!I366*1.1 -> 13072.396 | J366: =+'COMUNAS - HOME DELIVERY 2026'!J366*1.1 -> 17092.706 | K366: =+'COMUNAS - HOME DELIVERY 2026'!K366*1.1 -> 22560.397 | L366: =+'COMUNAS - HOME DELIVERY 2026'!L366*1.1 -> 26924.674 | M366: =+'COMUNAS - HOME DELIVERY 2026'!M366*1.1 -> 1145.9844 | N366: =+'COMUNAS - HOME DELIVERY 2026'!N366*1.1 -> 951.8652
C367: TARAPACA (I) | D367: PAM | E367: POZO ALMONTE | F367: =+'COMUNAS - HOME DELIVERY 2026'!F367*1.1 -> 9012.9204 | G367: =+'COMUNAS - HOME DELIVERY 2026'!G367*1.1 -> 9830.2644 | H367: =+'COMUNAS - HOME DELIVERY 2026'!H367*1.1 -> 10809.374 | I367: =+'COMUNAS - HOME DELIVERY 2026'!I367*1.1 -> 13072.396 | J367: =+'COMUNAS - HOME DELIVERY 2026'!J367*1.1 -> 17092.706 | K367: =+'COMUNAS - HOME DELIVERY 2026'!K367*1.1 -> 22560.397 | L367: =+'COMUNAS - HOME DELIVERY 2026'!L367*1.1 -> 26924.674 | M367: =+'COMUNAS - HOME DELIVERY 2026'!M367*1.1 -> 1145.9844 | N367: =+'COMUNAS - HOME DELIVERY 2026'!N367*1.1 -> 951.8652
C368: ANTOFAGASTA (II) | D368: ANF | E368: ANTOFAGASTA | F368: =+'COMUNAS - HOME DELIVERY 2026'!F368*1.1 -> 5767.9512 | G368: =+'COMUNAS - HOME DELIVERY 2026'!G368*1.1 -> 6166.4064 | H368: =+'COMUNAS - HOME DELIVERY 2026'!H368*1.1 -> 6778.2792 | I368: =+'COMUNAS - HOME DELIVERY 2026'!I368*1.1 -> 8196.144 | J368: =+'COMUNAS - HOME DELIVERY 2026'!J368*1.1 -> 10205.448 | K368: =+'COMUNAS - HOME DELIVERY 2026'!K368*1.1 -> 13471.418 | L368: =+'COMUNAS - HOME DELIVERY 2026'!L368*1.1 -> 16159.572 | M368: =+'COMUNAS - HOME DELIVERY 2026'!M368*1.1 -> 729.9336 | N368: =+'COMUNAS - HOME DELIVERY 2026'!N368*1.1 -> 601.656
... C397: MAGALLANES (XII) | D397: ATC | E397: ANTARTICA | F397: =+'COMUNAS - HOME DELIVERY 2026'!F397*1.1 -> 27147.74 | G397: =+'COMUNAS - HOME DELIVERY 2026'!G397*1.1 -> 28319.267 | H397: =+'COMUNAS - HOME DELIVERY 2026'!H397*1.1 -> 29814.325 | I397: =+'COMUNAS - HOME DELIVERY 2026'!I397*1.1 -> 32375.336 | J397: =+'COMUNAS - HOME DELIVERY 2026'!J397*1.1 -> 36118.091 | K397: =+'COMUNAS - HOME DELIVERY 2026'!K397*1.1 -> 42435.479 | L397: =+'COMUNAS - HOME DELIVERY 2026'!L397*1.1 -> 47193.102 | M397: =+'COMUNAS - HOME DELIVERY 2026'!M397*1.1 -> 1254.9636 | N397: =+'COMUNAS - HOME DELIVERY 2026'!N397*1.1 -> 968.8932
C399: Tarifa Servicio SAMEDAY
C400: REGION | E400: DESTINO | F400: 0 - 0.5 | G400: 0.5 - 1.5 | H400: 1.5 - 3 | I400: 3 - 6 | J400: 6 - 10 | K400: 10 - 16 | L400: 16 - 20 | M400: 20 - 50 * | N400: > 50 *
C401: REGION METROPOLITANA (XIII) | E401: SAMEDAY (RM) | F401: =+'COMUNAS - HOME DELIVERY 2026'!F401*1.1 -> 3661.02 | G401: =+'COMUNAS - HOME DELIVERY 2026'!G401*1.1 -> 3797.244 | H401: =+'COMUNAS - HOME DELIVERY 2026'!H401*1.1 -> 4042.4472 | I401: =+'COMUNAS - HOME DELIVERY 2026'!I401*1.1 -> 4401.1704 | J401: =+'COMUNAS - HOME DELIVERY 2026'!J401*1.1 -> 5097.048 | K401: =+'COMUNAS - HOME DELIVERY 2026'!K401*1.1 -> 5543.1816 | L401: =+'COMUNAS - HOME DELIVERY 2026'!L401*1.1 -> 6488.8032 | M401: =+'COMUNAS - HOME DELIVERY 2026'!M401*1.1 -> 511.9752 | N401: =+'COMUNAS - HOME DELIVERY 2026'!N401*1.1 -> 511.9752

Sheet CALCULADORA TELONES
B1: **SE TOMA EL VALOR MAYOR ENTRE PESO VOLUMEN Y PESO REAL
B4: Telón 100" + Trípode / Eléctrico
B5: Medidas | C5: Factor | D5: Peso Real | F5: Comuna | G5: Modelo | H5: Envío Neto | I5: Envío Bruto | J5: Envío a Cobrar
B6: =226*19*12 -> 51528 | C6: 4000 | G6: =+B14 -> Telón 60" | H6: =IFERROR(VLOOKUP($F$6,'COMUNAS - HOME DELIVERY 2026(2)'!$E$6:$L$353,5,FALSE),"Por Definir") -> Por Definir | I6: =IFERROR(H6*1.19,"Por Definir") -> Por Definir | J6: =IFERROR(CEILING(I6,1000+1000)-10,"Por Definir") -> Por Definir | K6: (ACTUALMENTE GRATIS)
B7: =B6/C6 -> 12.882 | C7: > | D7: 9 | G7: =+B9 -> Telón 100" | H7: =IFERROR(VLOOKUP($F$6,'COMUNAS - HOME DELIVERY 2026(2)'!$E$6:$L$353,6,FALSE),"Por Definir") -> Por Definir | I7: =IFERROR(H7*1.19,"Por Definir") -> Por Definir | J7: =IFERROR(CEILING(I7,1000+1000)-10,"Por Definir") -> Por Definir
G8: =+B4 -> Telón 100" + Trípode / Eléctrico | H8: =IFERROR(VLOOKUP($F$6,'COMUNAS - HOME DELIVERY 2026(2)'!$E$6:$L$353,7,FALSE),"Por Definir") -> Por Definir | I8: =IFERROR(H8*1.19,"Por Definir") -> Por Definir | J8: =IFERROR(CEILING(I8,1000+1000)-10,"Por Definir") -> Por Definir
B9: Telón 100" | F9: ESCRIBIR COMUNA AQUÍ (MAYÚSCULA SIN TÍLDE)
B10: Medidas | C10: Factor | D10: Peso Real
B11: =226*13*11 -> 32318 | C11: 4000
B12: =B11/C11 -> 8.0795 | C12: = | D12: 8
B14: Telón 60"
B15: Medidas | C15: Factor | D15: Peso Real
B16: =143*13*11 -> 20449 | C16: 4000
B17: =B16/C16 -> 5.11225 | C17: < | D17: 5
B21: Chimenea 40"
B22: Medidas | C22: Factor | D22: Peso Real | F22: Comuna | G22: Modelo | H22: Envío Neto | I22: Envío Bruto | J22: Envío a Cobrar
B23: =110.1*20.5*55 -> 124137.75 | C23: 4000 | G23: =+B21 -> Chimenea 40" | H23: =IFERROR(VLOOKUP($F$23,'COMUNAS - HOME DELIVERY 2026(2)'!$E$6:$N$353,8,FALSE)+((B24-20)*VLOOKUP(F23,'COMUNAS - HOME DELIVERY 2026(2)'!$E$6:$N$353,9,FALSE)),"Por Definir") -> Por Definir | I23: =IFERROR(H23*1.19,"Por Definir") -> Por Definir | J23: =IFERROR(CEILING(I23,1000+1000)-10,"Por Definir") -> Por Definir
B24: =B23/C23 -> 31.034437 | C24: > | D24: 19.5 | G24: =+B26 -> Chimenea 50" | H24: =IFERROR(VLOOKUP($F$23,'COMUNAS - HOME DELIVERY 2026(2)'!$E$6:$N$353,8,FALSE)+((B29-20)*VLOOKUP($F$23,'COMUNAS - HOME DELIVERY 2026(2)'!$E$6:$N$353,9,FALSE)),"Por Definir") -> Por Definir | I24: =IFERROR(H24*1.19,"Por Definir") -> Por Definir | J24: =IFERROR(CEILING(I24,1000+1000)-10,"Por Definir") -> Por Definir
G25: =+B31 -> Chimenea 60" | H25: =IFERROR(VLOOKUP($F$23,'COMUNAS - HOME DELIVERY 2026(2)'!$E$6:$N$353,8,FALSE)+((B34-20)*VLOOKUP($F$23,'COMUNAS - HOME DELIVERY 2026(2)'!$E$6:$N$353,9,FALSE)),"Por Definir") -> Por Definir | I25: =IFERROR(H25*1.19,"Por Definir") -> Por Definir | J25: =IFERROR(CEILING(I25,1000+1000)-10,"Por Definir") -> Por Definir
B26: Chimenea 50" | F26: ESCRIBIR COMUNA AQUÍ (MAYÚSCULA SIN TÍLDE)
B27: Medidas | C27: Factor | D27: Peso Real
B28: =136.8*20.5*55 -> 154242 | C28: 4000
B29: =B28/C28 -> 38.5605 | C29: > | D29: 24.5
B31: Chimenea 60"
B32: Medidas | C32: Factor | D32: Peso Real
B33: =160.9*22.2*55 -> 196458.9 | C33: 4000
B34: =B33/C33 -> 49.114725 | C34: > | D34: 30.5

Sheet CALCULADORA GRAL
B2: Peso (Kg) | D2: ESCRIBIR MAYOR APROXIMADO (EJ: 19,7 KG, ESCRIBIR 20 KG)
B3: Largo (Cm) | D3: ESCRIBIR MAYOR APROXIMADO (EJ: 5,4 CM, ESCRIBIR 5,5)
B4: Ancho (Cm) | D4: ESCRIBIR MAYOR APROXIMADO (EJ: 5,4 CM, ESCRIBIR 5,5) | F4: 0 | G4: 0.5 | H4: 1.5 | I4: 3 | J4: 6 | K4: 10 | L4: 16 | M4: 20 | N4: 50
B5: Alto (Cm) | D5: ESCRIBIR MAYOR APROXIMADO (EJ: 5,4 CM, ESCRIBIR 5,5) | F5: 2 | G5: 3 | H5: 4 | I5: 5 | J5: 6 | K5: 7 | L5: 8 | M5: 9 | N5: 10
B7: Comuna | D7: ESCRIBIR COMUNA
B9: Peso | C9: =+C2 -> 0
B10: Peso Volumen | C10: =(C3*C4*C5)/4000 -> 0
A12: PESO
B13: Comuna | C13: Envío Neto | D13: Envío Bruto | E13: Envío a Cobrar
B14: =+C7 -> 0 | C14: =IFERROR(IF(C9<20,VLOOKUP($B$14,'COMUNAS - HOME DELIVERY 2026(2)'!$E$6:$N$353,LOOKUP(C9,F4:N4,F5:N5),FALSE), VLOOKUP($B$14,'COMUNAS - HOME DELIVERY 2026(2)'!$E$6:$N$353,LOOKUP(C9,F4:N4,F5:N5)-1,FALSE)+(C9-20)*VLOOKUP(B14,'COMUNAS - HOME DELIVERY 2026(2)'!$E$6:$N$353,9,FALSE)),"Por definir") -> Por definir | D14: =IFERROR((C14*1.19)/(1-10%),"Por Definir") -> Por Definir | E14: =IFERROR(CEILING(D14,1000+1000)-10,"Por Definir") -> Por Definir | O14: COBRAR ESTO
A18: PESO VOLUMEN
B19: Comuna | C19: Envío Neto | D19: Envío Bruto | E19: Envío a Cobrar
B20: =+B14 -> 0 | C20: =IFERROR(IF(C10<20,VLOOKUP($B$20,'COMUNAS - HOME DELIVERY 2026(2)'!$E$6:$N$353,LOOKUP(C10,F4:N4,F5:N5),FALSE), VLOOKUP($B$20,'COMUNAS - HOME DELIVERY 2026(2)'!$E$6:$N$353,LOOKUP(C10,F4:N4,F5:N5)-1,FALSE)+(C10-20)*VLOOKUP(B20,'COMUNAS - HOME DELIVERY 2026(2)'!$E$6:$N$353,9,FALSE)),"Por definir") -> Por definir | D20: =IFERROR((C20*1.19)/(1-10%),"Por Definir") -> Por Definir | E20: =IFERROR(CEILING(D20,1000+1000)-10,"Por Definir") -> Por Definir | O20: COBRAR ESTO

Sheet TARIFAS PickUpPoint Delivery
B1: Propuesta generada el día 23 - 6 - 2025. Las tarifas tienen una vigencia de 2 meses para ser aceptadas.
B3: TARIFARIO DISTRIBUCIÓN
B6: PROPUESTA 2EBOX UM - DESTINO PUNTO BLUE
B7: Tarifas Servicio EXPRESS
B8: ORIGEN: SANTIAGO | C8: Quiebres de kilos | M8: Definiciones DISTRIBUCIÓN:
B9: DESTINO | C9: 0 - 0.5 | D9: 0.5 - 1.5 | E9: 1.5 - 3 | F9: 3 - 6 | G9: 6 - 10 | H9: 10 - 16 | I9: 16 - 20 | J9: 20 - 50 * | K9: > 50 * | M9: 🔵 Las tarifas son afectas a IVA
B10: COPIAPO | C10: 4181 | D10: 4658 | E10: 5357 | F10: 5816 | G10: 7544 | H10: 9631 | I10: 11243 | J10: 681 | K10: 559 | M10: 🔵 El tarifario considera Origen SANTIAGO y Destino Comuna radio BASE. También aplica para origen y destino en la misma ciudad.
B11: LA SERENA | C11: 3886 | D11: 4333 | E11: 4989 | F11: 5419 | G11: 6926 | H11: 8856 | I11: 10350 | J11: 671 | K11: 549 | M11: 🔵 El tarifario se mantiene para un Origen regiones (Comuna Región) y entrega en SANTIAGO.
B12: OVALLE | C12: 3886 | D12: 4333 | E12: 4989 | F12: 5419 | G12: 6926 | H12: 8856 | I12: 10350 | J12: 671 | K12: 549 | M12: 🔵 Para el cálculo de tarifas se mantienen los mismos ponderadores declarados para Home Delivery.
B13: LA CALERA | C13: 3325 | D13: 3551 | E13: 4294 | F13: 4820 | G13: 6227 | H13: 8026 | I13: 9286 | J13: 563 | K13: 473
B14: LOS ANDES | C14: 3287 | D14: 3510 | E14: 4245 | F14: 4767 | G14: 6160 | H14: 7942 | I14: 9193 | J14: 561 | K14: 471
B15: VINA DEL MAR | C15: 2411 | D15: 2603 | E15: 3089 | F15: 3557 | G15: 4659 | H15: 5650 | I15: 6556 | J15: 405 | K15: 336 | M15: 🔵 Tarifas válidas solo para envíos terrestres, no aplica para despachos aéreos para Extremos.
B16: SANTIAGO | C16: 2400 | D16: 2604 | E16: 2991 | F16: 3454 | G16: 4251 | H16: 5163 | I16: 6082 | J16: 381 | K16: 305 | M16: 🔵 El costo del envío está asociado al mayor valor entre el peso fisico y peso volumétrico. El peso volumétrico es igual a (largo*ancho*alto)/4.000.
B17: MELIPILLA | C17: 3233 | D17: 3478 | E17: 4097 | F17: 4696 | G17: 6104 | H17: 7368 | I17: 8523 | J17: 516 | K17: 428 | M17: 🔵 El kilo máximo admitido en Punto Pick up corresponde a 20 kg físico o cajas que no superen las dimensiones de 70x70x70 (cm)
B18: RANCAGUA | C18: 3287 | D18: 3510 | E18: 4245 | F18: 4767 | G18: 6160 | H18: 7942 | I18: 9193 | J18: 561 | K18: 471 | M18: Ejemplo: tarifa Santiago 8 kg´s = $4251.
B19: CURICO | C19: 3443 | D19: 3723 | E19: 4457 | F19: 4933 | G19: 6464 | H19: 8400 | I19: 9684 | J19: 571 | K19: 486
B20: TALCA | C20: 3443 | D20: 3723 | E20: 4457 | F20: 4933 | G20: 6464 | H20: 8400 | I20: 9684 | J20: 571 | K20: 486 | M20: Compromiso precio PUDO diferenciado:
B21: CHILLAN | C21: 3931 | D21: 4236 | E21: 4882 | F21: 5356 | G21: 6801 | H21: 8617 | I21: 10142 | J21: 690 | K21: 556 | M21: - La tarifa de entrega Punto PickUp y Estaciones COPEC se establece con el fin de incentivar la conversión de ventas y potenciar nuestra red. Este descuento debe verse reflejado proporcionalmente en el checkout.
B22: CONCEPCION | C22: 3931 | D22: 4236 | E22: 4882 | F22: 5356 | G22: 6801 | H22: 8617 | I22: 10142 | J22: 690 | K22: 556
B23: LOS ANGELES | C23: 4090 | D23: 4407 | E23: 5077 | F23: 5565 | G23: 7047 | H23: 8901 | I23: 10441 | J23: 693 | K23: 564
B24: TEMUCO | C24: 4263 | D24: 4508 | E24: 5202 | F24: 5663 | G24: 7302 | H24: 9198 | I24: 10747 | J24: 696 | K24: 568
B25: VALDIVIA | C25: 4631 | D25: 4982 | E25: 5706 | F25: 6051 | G25: 8019 | H25: 9745 | I25: 11326 | J25: 705 | K25: 588
B26: OSORNO | C26: 4631 | D26: 4982 | E26: 5706 | F26: 6051 | G26: 8019 | H26: 9745 | I26: 11326 | J26: 705 | K26: 588
B27: PUERTO MONTT | C27: 4514 | D27: 4855 | E27: 5564 | F27: 5965 | G27: 7797 | H27: 9536 | I27: 11118 | J27: 700 | K27: 575
B28: CASTRO | C28: 5110 | D28: 5769 | E28: 6653 | F28: 7634 | G28: 9190 | H28: 11699 | I28: 14521 | J28: 727 | K28: 594
B30: Extremos Terrestre - Tarifas Servicio EXPRESS
B31: DESTINO | C31: 0 - 0.5 | D31: 0.5 - 1.5 | E31: 1.5 - 3 | F31: 3 - 6 | G31: 6 - 10 | H31: 10 - 16 | I31: 16 - 20 | J31: 20 - 50 * | K31: > 50 *
B32: ARICA | C32: 5765 | D32: 6630 | E32: 7345 | F32: 8998 | G32: 11940 | H32: 18195 | I32: 21699 | J32: 856 | K32: 703
B33: IQUIQUE | C33: 5473 | D33: 6159 | E33: 6828 | F33: 8374 | G33: 11123 | H33: 16132 | I33: 19362 | J33: 840 | K33: 671
B34: CALAMA | C34: 5473 | D34: 6159 | E34: 6828 | F34: 8374 | G34: 11123 | H34: 16132 | I34: 19362 | J34: 840 | K34: 671
B35: ANTOFAGASTA | C35: 5231 | D35: 5761 | E35: 6389 | F35: 7843 | G35: 9904 | H35: 14391 | I35: 17376 | J35: 804 | K35: 636
B36: COYHAIQUE | C36: 6214 | D36: 7157 | E36: 8179 | F36: 9930 | G36: 12488 | H36: 20118 | I36: 23992 | J36: 918 | K36: 683
B37: PUNTA ARENAS | C37: 6214 | D37: 7157 | E37: 8179 | F37: 9930 | G37: 12488 | H37: 20118 | I37: 23992 | J37: 918 | K37: 683

Sheet COMUNAS - HOME DELIVERY 2025
C2: PROPUESTA 2EBOX UM - HOME DELIVERY (VALORES 2025)
C3: Tarifas Servicio EXPRESS - PRIORITY
C4: ORIGEN: SANTIAGO | F4: 1 | G4: 2 | H4: 3 | I4: 4 | J4: 5 | K4: 6 | L4: 7 | M4: 8 | N4: 9
C5: REGION | D5: POSTA | E5: COMUNA DESTINO | F5: 0 - 0.5 | G5: 0.5 - 1.5 | H5: 1.5 - 3 | I5: 3 - 6 | J5: 6 - 10 | K5: 10 - 16 | L5: 16 - 20 | M5: 20 - 50 * | N5: > 50 *
C6: METROPOLITANA (XIII) | D6: SCL | E6: SANTIAGO | F6: 2932 | G6: 3041 | H6: 3237 | I6: 3524 | J6: 4081 | K6: 4439 | L6: 5197 | M6: 300 | N6: 229 | P6: Aumento Tarifa Enero 2026
C7: METROPOLITANA (XIII) | D7: RLT | E7: RECOLETA | F7: 2932 | G7: 3041 | H7: 3237 | I7: 3524 | J7: 4081 | K7: 4439 | L7: 5197 | M7: 300 | N7: 229 | P7: 0.032 | Q7: 1.032
C8: METROPOLITANA (XIII) | D8: IDP | E8: INDEPENDENCIA | F8: 2932 | G8: 3041 | H8: 3237 | I8: 3524 | J8: 4081 | K8: 4439 | L8: 5197 | M8: 300 | N8: 229
C9: METROPOLITANA (XIII) | D9: QTN | E9: QUINTA NORMAL | F9: 2932 | G9: 3041 | H9: 3237 | I9: 3524 | J9: 4081 | K9: 4439 | L9: 5197 | M9: 300 | N9: 229
C10: METROPOLITANA (XIII) | D10: MAI | E10: MAIPU | F10: 2932 | G10: 3041 | H10: 3237 | I10: 3524 | J10: 4081 | K10: 4439 | L10: 5197 | M10: 300 | N10: 229
C11: METROPOLITANA (XIII) | D11: PUD | E11: PUDAHUEL | F11: 2932 | G11: 3041 | H11: 3237 | I11: 3524 | J11: 4081 | K11: 4439 | L11: 5197 | M11: 300 | N11: 229
C12: METROPOLITANA (XIII) | D12: REN | E12: RENCA | F12: 2932 | G12: 3041 | H12: 3237 | I12: 3524 | J12: 4081 | K12: 4439 | L12: 5197 | M12: 300 | N12: 229
C13: METROPOLITANA (XIII) | D13: QLC | E13: QUILICURA | F13: 2932 | G13: 3041 | H13: 3237 | I13: 3524 | J13: 4081 | K13: 4439 | L13: 5197 | M13: 300 | N13: 229
C14: METROPOLITANA (XIII) | D14: CNH | E14: CONCHALI | F14: 2932 | G14: 3041 | H14: 3237 | I14: 3524 | J14: 4081 | K14: 4439 | L14: 5197 | M14: 300 | N14: 229
C15: METROPOLITANA (XIII) | D15: LPR | E15: LO PRADO | F15: 2932 | G15: 3041 | H15: 3237 | I15: 3524 | J15: 4081 | K15: 4439 | L15: 5197 | M15: 300 | N15: 229
C16: METROPOLITANA (XIII) | D16: CNV | E16: CERRO NAVIA | F16: 2932 | G16: 3041 | H16: 3237 | I16: 3524 | J16: 4081 | K16: 4439 | L16: 5197 | M16: 300 | N16: 229
C17: METROPOLITANA (XIII) | D17: ECE | E17: ESTACION CENTRAL | F17: 2932 | G17: 3041 | H17: 3237 | I17: 3524 | J17: 4081 | K17: 4439 | L17: 5197 | M17: 300 | N17: 229
C18: METROPOLITANA (XIII) | D18: HRB | E18: HUECHURABA | F18: 2932 | G18: 3041 | H18: 3237 | I18: 3524 | J18: 4081 | K18: 4439 | L18: 5197 | M18: 300 | N18: 229
C19: METROPOLITANA (XIII) | D19: RRI | E19: CERRILLOS | F19: 2932 | G19: 3041 | H19: 3237 | I19: 3524 | J19: 4081 | K19: 4439 | L19: 5197 | M19: 300 | N19: 229
... C71: COQUIMBO (IV) | D71: ILL | E71: ILLAPEL | F71: 3710 | G71: 3925 | H71: 4542 | I71: 5282 | J71: 6529 | K71: 7847 | L71: 8814 | M71: 447 | N71: 376
C72: COQUIMBO (IV) | D72: LSC | E72: LA SERENA | F72: 4244 | G72: 4672 | H72: 5192 | I72: 5869 | J72: 7201 | K72: 8604 | L72: 9767 | M72: 532 | N72: 436 | Q72: 9767
C73: COQUIMBO (IV) | D73: LHC | E73: LA HIGUERA | F73: 4244 | G73: 4672 | H73: 5192 | I73: 5869 | J73: 7201 | K73: 8604 | L73: 9767 | M73: 532 | N73: 436 | Q73: =11*M72 -> 5852
C74: COQUIMBO (IV) | D74: LVL | E74: LOS VILOS | F74: 3710 | G74: 3925 | H74: 4542 | I74: 5282 | J74: 6529 | K74: 7847 | L74: 8814 | M74: 447 | N74: 376 | Q74: =Q72+Q73 -> 15619
C75: COQUIMBO (IV) | D75: MPC | E75: MONTE PATRIA | F75: 6457.5 | G75: 7111.5 | H75: 7900.5 | I75: 8932.5 | J75: 10696.5 | K75: 12924 | L75: 14671.5 | M75: 799.5 | N75: 655.5
C76: COQUIMBO (IV) | D76: OVL | E76: OVALLE | F76: 4305 | G76: 4741 | H76: 5267 | I76: 5955 | J76: 7131 | K76: 8616 | L76: 9781 | M76: 533 | N76: 437
C77: COQUIMBO (IV) | D77: PHO | E77: PAIGUANO | F77: 6366 | G77: 7008 | H77: 7788 | I77: 8803.5 | J77: 10801.5 | K77: 12906 | L77: 14650.5 | M77: 798 | N77: 654
C78: COQUIMBO (IV) | D78: PTQ | E78: PUNITAQUI | F78: 4305 | G78: 4741 | H78: 5267 | I78: 5955 | J78: 7131 | K78: 8616 | L78: 9781 | M78: 533 | N78: 437
C79: COQUIMBO (IV) | D79: RHU | E79: RIO HURTADO | F79: 6457.5 | G79: 7111.5 | H79: 7900.5 | I79: 8932.5 | J79: 10696.5 | K79: 12924 | L79: 14671.5 | M79: 799.5 | N79: 655.5
C80: COQUIMBO (IV) | D80: SCA | E80: SALAMANCA | F80: 5565 | G80: 5887.5 | H80: 6813 | I80: 7923 | J80: 9793.5 | K80: 11770.5 | L80: 13221 | M80: 670.5 | N80: 564
C81: COQUIMBO (IV) | D81: VCA | E81: VICUNA | F81: 4244 | G81: 4672 | H81: 5192 | I81: 5869 | J81: 7201 | K81: 8604 | L81: 9767 | M81: 532 | N81: 436
C82: VALPARAISO (V) | D82: KNA | E82: VINA DEL MAR | F82: 3589 | G82: 3839 | H82: 4357 | I82: 5160 | J82: 6411 | K82: 7245 | L82: 8131 | M82: 410 | N82: 340
C83: VALPARAISO (V) | D83: ABO | E83: ALGARROBO | F83: 3589 | G83: 3839 | H83: 4357 | I83: 5160 | J83: 6411 | K83: 7245 | L83: 8131 | M83: 410 | N83: 340
C84: VALPARAISO (V) | D84: CDO | E84: CABILDO | F84: 3710 | G84: 3925 | H84: 4542 | I84: 5282 | J84: 6529 | K84: 7847 | L84: 8814 | M84: 447 | N84: 376
C85: VALPARAISO (V) | D85: CLG | E85: CALLE LARGA | F85: 3673 | G85: 3886 | H85: 4496 | I85: 5230 | J85: 6465 | K85: 7769 | L85: 8731 | M85: 445 | N85: 374
C86: VALPARAISO (V) | D86: CRT | E86: CARTAGENA | F86: 3589 | G86: 3839 | H86: 4357 | I86: 5160 | J86: 6411 | K86: 7245 | L86: 8131 | M86: 410 | N86: 340
... C238: ARAUCANIA (IX) | D238: ZOL | E238: ANGOL | F238: 4440 | G238: 4743 | H238: 5274 | I238: 6013 | J238: 7319 | K238: 8646 | L238: 9847 | M238: 550 | N238: 448
C239: ARAUCANIA (IX) | D239: CRH | E239: CARAHUE | F239: 4604 | G239: 4839 | H239: 5391 | I239: 6109 | J239: 7563 | K239: 8917 | L239: 10121 | M239: 552 | N239: 451 | P239: ñuble
C240: ARAUCANIA (IX) | D240: CHL | E240: CHOL CHOL | F240: 6906 | G240: 7258.5 | H240: 8086.5 | I240: 9163.5 | J240: 11344.5 | K240: 13375.5 | L240: 15181.5 | M240: 828 | N240: 676.5
C241: ARAUCANIA (IX) | D241: CPI | E241: COLLIPULLI | F241: 4440 | G241: 4743 | H241: 5274 | I241: 6013 | J241: 7319 | K241: 8646 | L241: 9847 | M241: 550 | N241: 448
C242: ARAUCANIA (IX) | D242: NCO | E242: CUNCO | F242: 4604 | G242: 4839 | H242: 5391 | I242: 6109 | J242: 7563 | K242: 8917 | L242: 10121 | M242: 552 | N242: 451
C243: ARAUCANIA (IX) | D243: CCC | E243: CURACAUTIN | F243: 6906 | G243: 7258.5 | H243: 8086.5 | I243: 9163.5 | J243: 11344.5 | K243: 13375.5 | L243: 15181.5 | M243: 828 | N243: 676.5
C244: ARAUCANIA (IX) | D244: RRH | E244: CURARREHUE | F244: 6906 | G244: 7258.5 | H244: 8086.5 | I244: 9163.5 | J244: 11344.5 | K244: 13375.5 | L244: 15181.5 | M244: 828 | N244: 676.5
C245: ARAUCANIA (IX) | D245: ERL | E245: ERCILLA | F245: 4604 | G245: 4839 | H245: 5391 | I245: 6109 | J245: 7563 | K245: 8917 | L245: 10121 | M245: 552 | N245: 451
C246: ARAUCANIA (IX) | D246: FIE | E246: FREIRE | F246: 4604 | G246: 4839 | H246: 5391 | I246: 6109 | J246: 7563 | K246: 8917 | L246: 10121 | M246: 552 | N246: 451
C247: ARAUCANIA (IX) | D247: GAL | E247: GALVARINO | F247: 4604 | G247: 4839 | H247: 5391 | I247: 6109 | J247: 7563 | K247: 8917 | L247: 10121 | M247: 552 | N247: 451
C248: ARAUCANIA (IX) | D248: GEA | E248: GORBEA | F248: 4604 | G248: 4839 | H248: 5391 | I248: 6109 | J248: 7563 | K248: 8917 | L248: 10121 | M248: 552 | N248: 451
C249: ARAUCANIA (IX) | D249: LTR | E249: LAUTARO | F249: 4604 | G249: 4839 | H249: 5391 | I249: 6109 | J249: 7563 | K249: 8917 | L249: 10121 | M249: 552 | N249: 451
C250: ARAUCANIA (IX) | D250: LOC | E250: LONCOCHE | F250: 4604 | G250: 4839 | H250: 5391 | I250: 6109 | J250: 7563 | K250: 8917 | L250: 10121 | M250: 552 | N250: 451
C251: ARAUCANIA (IX) | D251: LQY | E251: LONQUIMAY | F251: 6906 | G251: 7258.5 | H251: 8086.5 | I251: 9163.5 | J251: 11344.5 | K251: 13375.5 | L251: 15181.5 | M251: 828 | N251: 676.5
... C310: LOS LAGOS (X) | D310: SPL | E310: SAN PABLO | F310: 4956 | G310: 5291 | H310: 5863 | I310: 6489 | J310: 8253 | K310: 9418 | L310: 10641 | M310: 560 | N310: 466
C311: Extremos Aéreos - Tarifas Servicio PRIORITY
C312: REGION | D312: POSTA | E312: COMUNA DESTINO | F312: 0 - 0.5 | G312: 0.5 - 1.5 | H312: 1.5 - 3 | I312: 3 - 6 | J312: 6 - 10 | K312: 10 - 16 | L312: 16 - 20 | M312: 20 - 50 * | N312: > 50 *
C313: ARICA Y PARINACOTA (XV) | D313: ARI | E313: ARICA | F313: 6099 | G313: 7189 | H313: 8703 | I313: 10294 | J313: 17165 | K313: 26933 | L313: 31578 | M313: 1559 | N313: 1505
C314: ARICA Y PARINACOTA (XV) | D314: CAM | E314: CAMARONES | F314: 24148.5 | G314: 25783.5 | H314: 28054.5 | I314: 30441 | J314: 40747.5 | K314: 55399.5 | L314: 62367 | M314: 2338.5 | N314: 2257.5
C315: ARICA Y PARINACOTA (XV) | D315: LGR | E315: GENERAL LAGOS | F315: 24148.5 | G315: 25783.5 | H315: 28054.5 | I315: 30441 | J315: 40747.5 | K315: 55399.5 | L315: 62367 | M315: 2338.5 | N315: 2257.5
C316: ARICA Y PARINACOTA (XV) | D316: PTR | E316: PUTRE | F316: 24148.5 | G316: 25783.5 | H316: 28054.5 | I316: 30441 | J316: 40747.5 | K316: 55399.5 | L316: 62367 | M316: 2338.5 | N316: 2257.5
C317: TARAPACA (I) | D317: IQQ | E317: IQUIQUE | F317: 5701 | G317: 6719 | H317: 8135 | I317: 9620 | J317: 16041 | K317: 25174 | L317: 29712 | M317: 1512 | N317: 1422
C318: TARAPACA (I) | D318: AHP | E318: ALTO HOSPICIO | F318: 5701 | G318: 6719 | H318: 8135 | I318: 9620 | J318: 16041 | K318: 25174 | L318: 29712 | M318: 1512 | N318: 1422
C319: TARAPACA (I) | D319: CMN | E319: CAMINA | F319: 23551.5 | G319: 25078.5 | H319: 27202.5 | I319: 29430 | J319: 39061.5 | K319: 52761 | L319: 59568 | M319: 2268 | N319: 2133
C320: TARAPACA (I) | D320: COE | E320: COLCHANE | F320: 23551.5 | G320: 25078.5 | H320: 27202.5 | I320: 29430 | J320: 39061.5 | K320: 52761 | L320: 59568 | M320: 2268 | N320: 2133
C321: TARAPACA (I) | D321: HRA | E321: HUARA | F321: 8551.5 | G321: 10078.5 | H321: 12202.5 | I321: 14430 | J321: 24061.5 | K321: 37761 | L321: 44568 | M321: 2268 | N321: 2133
C322: TARAPACA (I) | D322: OPC | E322: PICA | F322: 8551.5 | G322: 10078.5 | H322: 12202.5 | I322: 14430 | J322: 24061.5 | K322: 37761 | L322: 44568 | M322: 2268 | N322: 2133
C323: TARAPACA (I) | D323: PAM | E323: POZO ALMONTE | F323: 8551.5 | G323: 10078.5 | H323: 12202.5 | I323: 14430 | J323: 24061.5 | K323: 37761 | L323: 44568 | M323: 2268 | N323: 2133
C324: ANTOFAGASTA (II) | D324: ANF | E324: ANTOFAGASTA | F324: 5517 | G324: 6381 | H324: 7728 | I324: 9139 | J324: 15240 | K324: 23914 | L324: 28296 | M324: 1443 | N324: 1346
... C353: MAGALLANES (XII) | D353: ATC | E353: ANTARTICA | F353: 24298.5 | G353: 25876.5 | H353: 28161 | I353: 29973 | J353: 40521 | K353: 57300 | L353: 64813.5 | M353: 2577 | N353: 2430
C355: Extremos Terrestre - Tarifas Servicio EXPRESS
C356: REGION | D356: POSTA | E356: COMUNA DESTINO | F356: 0 - 0.5 | G356: 0.5 - 1.5 | H356: 1.5 - 3 | I356: 3 - 6 | J356: 6 - 10 | K356: 10 - 16 | L356: 16 - 20 | M356: 20 - 50 * | N356: > 50 *
C357: ARICA Y PARINACOTA (XV) | D357: ARI | E357: ARICA | F357: 5549 | G357: 6178 | H357: 6792 | I357: 8213 | J357: 10740 | K357: 14176 | L357: 16826 | M357: 685 | N357: 585
C358: ARICA Y PARINACOTA (XV) | D358: CAM | E358: CAMARONES | F358: 23323.5 | G358: 24267 | H358: 25188 | I358: 27319.5 | J358: 31110 | K358: 36264 | L358: 40239 | M358: 1027.5 | N358: 877.5
C359: ARICA Y PARINACOTA (XV) | D359: LGR | E359: GENERAL LAGOS | F359: 23323.5 | G359: 24267 | H359: 25188 | I359: 27319.5 | J359: 31110 | K359: 36264 | L359: 40239 | M359: 1027.5 | N359: 877.5
C360: ARICA Y PARINACOTA (XV) | D360: PTR | E360: PUTRE | F360: 23323.5 | G360: 24267 | H360: 25188 | I360: 27319.5 | J360: 31110 | K360: 36264 | L360: 40239 | M360: 1027.5 | N360: 877.5
C361: TARAPACA (I) | D361: IQQ | E361: IQUIQUE | F361: 5293 | G361: 5773 | H361: 6348 | I361: 7677 | J361: 10038 | K361: 13249 | L361: 15812 | M361: 673 | N361: 559
C362: TARAPACA (I) | D362: AHP | E362: ALTO HOSPICIO | F362: 5293 | G362: 5773 | H362: 6348 | I362: 7677 | J362: 10038 | K362: 13249 | L362: 15812 | M362: 673 | N362: 559
C363: TARAPACA (I) | D363: CMN | E363: CAMINA | F363: 22939.5 | G363: 23659.5 | H363: 24522 | I363: 26515.5 | J363: 30057 | K363: 34873.5 | L363: 38718 | M363: 1009.5 | N363: 838.5
C364: TARAPACA (I) | D364: COE | E364: COLCHANE | F364: 22939.5 | G364: 23659.5 | H364: 24522 | I364: 26515.5 | J364: 30057 | K364: 34873.5 | L364: 38718 | M364: 1009.5 | N364: 838.5
C365: TARAPACA (I) | D365: HRA | E365: HUARA | F365: 7939.5 | G365: 8659.5 | H365: 9522 | I365: 11515.5 | J365: 15057 | K365: 19873.5 | L365: 23718 | M365: 1009.5 | N365: 838.5
C366: TARAPACA (I) | D366: OPC | E366: PICA | F366: 7939.5 | G366: 8659.5 | H366: 9522 | I366: 11515.5 | J366: 15057 | K366: 19873.5 | L366: 23718 | M366: 1009.5 | N366: 838.5
C367: TARAPACA (I) | D367: PAM | E367: POZO ALMONTE | F367: 7939.5 | G367: 8659.5 | H367: 9522 | I367: 11515.5 | J367: 15057 | K367: 19873.5 | L367: 23718 | M367: 1009.5 | N367: 838.5
C368: ANTOFAGASTA (II) | D368: ANF | E368: ANTOFAGASTA | F368: 5081 | G368: 5432 | H368: 5971 | I368: 7220 | J368: 8990 | K368: 11867 | L368: 14235 | M368: 643 | N368: 530
... C397: MAGALLANES (XII) | D397: ATC | E397: ANTARTICA | F397: 23914.5 | G397: 24946.5 | H397: 26263.5 | I397: 28519.5 | J397: 31816.5 | K397: 37381.5 | L397: 41572.5 | M397: 1105.5 | N397: 853.5
C399: Tarifa Servicio SAMEDAY
C400: REGION | E400: DESTINO | F400: 0 - 0.5 | G400: 0.5 - 1.5 | H400: 1.5 - 3 | I400: 3 - 6 | J400: 6 - 10 | K400: 10 - 16 | L400: 16 - 20 | M400: 20 - 50 * | N400: > 50 *
C401: REGION METROPOLITANA (XIII) | E401: SAMEDAY (RM) | F401: 3225 | G401: 3345 | H401: 3561 | I401: 3877 | J401: 4490 | K401: 4883 | L401: 5716 | M401: 451 | N401: 451

Sheet COMUNAS - PickUpPoint Delivery
C2: PROPUESTA 2EBOX UM - DESTINO PUNTO BLUE | P2: Definiciones DISTRIBUCIÓN:
C3: Tarifas Servicio EXPRESS | P3: 🔵 Las tarifas son afectas a IVA
C4: ORIGEN: SANTIAGO | F4: 1 | G4: 2 | H4: 3 | I4: 4 | J4: 5 | K4: 6 | L4: 7 | M4: 8 | N4: 9 | P4: 🔵 El tarifario considera Origen SANTIAGO y Destino Comuna. También aplica para origen y destino en la misma ciudad.
C5: REGION | D5: POSTA | E5: COMUNA DESTINO | F5: 0 - 0.5 | G5: 0.5 - 1.5 | H5: 1.5 - 3 | I5: 3 - 6 | J5: 6 - 10 | K5: 10 - 16 | L5: 16 - 20 | M5: 20 - 50 * | N5: > 50 * | P5: 🔵 Envios a Comunas BORDER considera un costo fijo de $15000 adicional a la tarifa (ya incluido).
C6: METROPOLITANA (XIII) | D6: SCL | E6: SANTIAGO | F6: 2400 | G6: 2604 | H6: 2991 | I6: 3454 | J6: 4251 | K6: 5163 | L6: 6082 | M6: 381 | N6: 305
C7: METROPOLITANA (XIII) | D7: RLT | E7: RECOLETA | F7: 2400 | G7: 2604 | H7: 2991 | I7: 3454 | J7: 4251 | K7: 5163 | L7: 6082 | M7: 381 | N7: 305
C8: METROPOLITANA (XIII) | D8: IDP | E8: INDEPENDENCIA | F8: 2400 | G8: 2604 | H8: 2991 | I8: 3454 | J8: 4251 | K8: 5163 | L8: 6082 | M8: 381 | N8: 305 | P8: 🔵 Tarifas válidas solo para envíos terrestres, no aplica para despachos aéreos para Extremos.
C9: METROPOLITANA (XIII) | D9: QTN | E9: QUINTA NORMAL | F9: 2400 | G9: 2604 | H9: 2991 | I9: 3454 | J9: 4251 | K9: 5163 | L9: 6082 | M9: 381 | N9: 305 | P9: 🔵 El costo del envío esta asociado al mayor valor entre el peso físico y peso volumetrico. El peso volumetrico es igual a (largo*ancho*alto)/4.000.
C10: METROPOLITANA (XIII) | D10: MAI | E10: MAIPU | F10: 2400 | G10: 2604 | H10: 2991 | I10: 3454 | J10: 4251 | K10: 5163 | L10: 6082 | M10: 381 | N10: 305 | P10: 🔵 El kilo máximo admitido en Punto Pick up corresponde a 20 kg físico o cajas que no superen las dimensiones de 70x70x70 (cm)
C11: METROPOLITANA (XIII) | D11: PUD | E11: PUDAHUEL | F11: 2400 | G11: 2604 | H11: 2991 | I11: 3454 | J11: 4251 | K11: 5163 | L11: 6082 | M11: 381 | N11: 305 | P11: Ejemplo: tarifa Pudahuel 8 kg´s = $4251.
C12: METROPOLITANA (XIII) | D12: REN | E12: RENCA | F12: 2400 | G12: 2604 | H12: 2991 | I12: 3454 | J12: 4251 | K12: 5163 | L12: 6082 | M12: 381 | N12: 305
C13: METROPOLITANA (XIII) | D13: QLC | E13: QUILICURA | F13: 2400 | G13: 2604 | H13: 2991 | I13: 3454 | J13: 4251 | K13: 5163 | L13: 6082 | M13: 381 | N13: 305 | P13: Compromiso precio PUDO diferenciado:
C14: METROPOLITANA (XIII) | D14: CNH | E14: CONCHALI | F14: 2400 | G14: 2604 | H14: 2991 | I14: 3454 | J14: 4251 | K14: 5163 | L14: 6082 | M14: 381 | N14: 305 | P14: - La tarifa de entrega Punto PickUp y Estaciones COPEC se establece con el fin de incentivar la conversión de ventas y potenciar nuestra red. Este descuento debe verse reflejado proporcionalmente en el checkout.
C15: METROPOLITANA (XIII) | D15: LPR | E15: LO PRADO | F15: 2400 | G15: 2604 | H15: 2991 | I15: 3454 | J15: 4251 | K15: 5163 | L15: 6082 | M15: 381 | N15: 305
C16: METROPOLITANA (XIII) | D16: CNV | E16: CERRO NAVIA | F16: 2400 | G16: 2604 | H16: 2991 | I16: 3454 | J16: 4251 | K16: 5163 | L16: 6082 | M16: 381 | N16: 305
C17: METROPOLITANA (XIII) | D17: ECE | E17: ESTACION CENTRAL | F17: 2400 | G17: 2604 | H17: 2991 | I17: 3454 | J17: 4251 | K17: 5163 | L17: 6082 | M17: 381 | N17: 305
C18: METROPOLITANA (XIII) | D18: HRB | E18: HUECHURABA | F18: 2400 | G18: 2604 | H18: 2991 | I18: 3454 | J18: 4251 | K18: 5163 | L18: 6082 | M18: 381 | N18: 305
C19: METROPOLITANA (XIII) | D19: RRI | E19: CERRILLOS | F19: 2400 | G19: 2604 | H19: 2991 | I19: 3454 | J19: 4251 | K19: 5163 | L19: 6082 | M19: 381 | N19: 305
C20: METROPOLITANA (XIII) | D20: SPO | E20: SAN PEDRO | F20: 3233 | G20: 3478 | H20: 4097 | I20: 4696 | J20: 6104 | K20: 7368 | L20: 8523 | M20: 516 | N20: 428
C21: METROPOLITANA (XIII) | D21: PRO | E21: PROVIDENCIA | F21: 2400 | G21: 2604 | H21: 2991 | I21: 3454 | J21: 4251 | K21: 5163 | L21: 6082 | M21: 381 | N21: 305
C22: METROPOLITANA (XIII) | D22: NNA | E22: NUNOA | F22: 2400 | G22: 2604 | H22: 2991 | I22: 3454 | J22: 4251 | K22: 5163 | L22: 6082 | M22: 381 | N22: 305
C23: METROPOLITANA (XIII) | D23: LCD | E23: LAS CONDES | F23: 2400 | G23: 2604 | H23: 2991 | I23: 3454 | J23: 4251 | K23: 5163 | L23: 6082 | M23: 381 | N23: 305
C24: METROPOLITANA (XIII) | D24: LFD | E24: LA FLORIDA | F24: 2400 | G24: 2604 | H24: 2991 | I24: 3454 | J24: 4251 | K24: 5163 | L24: 6082 | M24: 381 | N24: 305
C25: METROPOLITANA (XIII) | D25: LRN | E25: LA REINA | F25: 2400 | G25: 2604 | H25: 2991 | I25: 3454 | J25: 4251 | K25: 5163 | L25: 6082 | M25: 381 | N25: 305
C26: METROPOLITANA (XIII) | D26: MAC | E26: MACUL | F26: 2400 | G26: 2604 | H26: 2991 | I26: 3454 | J26: 4251 | K26: 5163 | L26: 6082 | M26: 381 | N26: 305
... C310: LOS LAGOS (X) | D310: SPL | E310: SAN PABLO | F310: 4631 | G310: 4982 | H310: 5706 | I310: 6051 | J310: 8019 | K310: 9745 | L310: 11326 | M310: 705 | N310: 588
C312: Extremos Terrestre - Tarifas Servicio EXPRESS
C313: REGION | D313: POSTA | E313: COMUNA DESTINO | F313: 0 - 0.5 | G313: 0.5 - 1.5 | H313: 1.5 - 3 | I313: 3 - 6 | J313: 6 - 10 | K313: 10 - 16 | L313: 16 - 20 | M313: 20 - 50 * | N313: > 50 *
C314: ARICA Y PARINACOTA (XV) | D314: ARI | E314: ARICA | F314: 5765 | G314: 6630 | H314: 7345 | I314: 8998 | J314: 11940 | K314: 18195 | L314: 21699 | M314: 856 | N314: 703
C315: ARICA Y PARINACOTA (XV) | D315: CAM | E315: CAMARONES | F315: 23647.5 | G315: 24945 | H315: 26017.5 | I315: 28497 | J315: 32910 | K315: 42292.5 | L315: 47548.5 | M315: 1284 | N315: 1054.5
C316: ARICA Y PARINACOTA (XV) | D316: LGR | E316: GENERAL LAGOS | F316: 23647.5 | G316: 24945 | H316: 26017.5 | I316: 28497 | J316: 32910 | K316: 42292.5 | L316: 47548.5 | M316: 1284 | N316: 1054.5
C317: ARICA Y PARINACOTA (XV) | D317: PTR | E317: PUTRE | F317: 23647.5 | G317: 24945 | H317: 26017.5 | I317: 28497 | J317: 32910 | K317: 42292.5 | L317: 47548.5 | M317: 1284 | N317: 1054.5
C318: TARAPACA (I) | D318: IQQ | E318: IQUIQUE | F318: 5473 | G318: 6159 | H318: 6828 | I318: 8374 | J318: 11123 | K318: 16132 | L318: 19362 | M318: 840 | N318: 671
C319: TARAPACA (I) | D319: AHP | E319: ALTO HOSPICIO | F319: 5473 | G319: 6159 | H319: 6828 | I319: 8374 | J319: 11123 | K319: 16132 | L319: 19362 | M319: 840 | N319: 671
C320: TARAPACA (I) | D320: CMN | E320: CAMINA | F320: 23209.5 | G320: 24238.5 | H320: 25242 | I320: 27561 | J320: 31684.5 | K320: 39198 | L320: 44043 | M320: 1260 | N320: 1006.5
C321: TARAPACA (I) | D321: COE | E321: COLCHANE | F321: 23209.5 | G321: 24238.5 | H321: 25242 | I321: 27561 | J321: 31684.5 | K321: 39198 | L321: 44043 | M321: 1260 | N321: 1006.5
C322: TARAPACA (I) | D322: HRA | E322: HUARA | F322: 8209.5 | G322: 9238.5 | H322: 10242 | I322: 12561 | J322: 16684.5 | K322: 24198 | L322: 29043 | M322: 1260 | N322: 1006.5
C323: TARAPACA (I) | D323: OPC | E323: PICA | F323: 8209.5 | G323: 9238.5 | H323: 10242 | I323: 12561 | J323: 16684.5 | K323: 24198 | L323: 29043 | M323: 1260 | N323: 1006.5
C324: TARAPACA (I) | D324: PAM | E324: POZO ALMONTE | F324: 8209.5 | G324: 9238.5 | H324: 10242 | I324: 12561 | J324: 16684.5 | K324: 24198 | L324: 29043 | M324: 1260 | N324: 1006.5
C325: ANTOFAGASTA (II) | D325: ANF | E325: ANTOFAGASTA | F325: 5231 | G325: 5761 | H325: 6389 | I325: 7843 | J325: 9904 | K325: 14391 | L325: 17376 | M325: 804 | N325: 636
... C354: MAGALLANES (XII) | D354: ATC | E354: ANTARTICA | F354: 24321 | G354: 25735.5 | H354: 27268.5 | I354: 29895 | J354: 33732 | K354: 45177 | L354: 50988 | M354: 1377 | N354: 1024.5

Sheet DICCIONARIO COMUNAS
I1: MATRIZ DE TRANSITO (ÚLTIMA MILLA)
H2: SANTIAGO | I2: ORIGEN: SANTIAGO | K2: Posibilidad SDD
B3: COD REGION | C3: NOM REGION | D3: COD COMUNA | E3: NOM COMUNA | F3: POSTA COMUNA | G3: Base | H3: Radio_COMUNA | I3: EXPRESS | J3: PRIORITY | K3: SAMEDAY (SDD) | L3: *Tiempos de promesa sujetos a revisión según realidad de los tiempos de despachos.
B4: 15 | C4: Arica y Parinacota | D4: 15101 | E4: ARICA | F4: ARI | G4: ARICA | H4: BASE | I4: 4 | J4: 2 | K4: NO
B5: 15 | C5: Arica y Parinacota | D5: 15102 | E5: CAMARONES | F5: CAM | G5: ARICA | H5: BORDER | I5: 7 | J5: 5 | K5: NO
B6: 15 | C6: Arica y Parinacota | D6: 15202 | E6: GENERAL LAGOS | F6: LGR | G6: ARICA | H6: BORDER | I6: 7 | J6: 5 | K6: NO
B7: 15 | C7: Arica y Parinacota | D7: 15201 | E7: PUTRE | F7: PTR | G7: ARICA | H7: BORDER | I7: 7 | J7: 5 | K7: NO
B8: 1 | C8: Tarapacá | D8: 1107 | E8: ALTO HOSPICIO | F8: AHP | G8: IQUIQUE | H8: INFLUENCIA | I8: 4 | J8: 3 | K8: NO
B9: 1 | C9: Tarapacá | D9: 1402 | E9: CAMINA | F9: CMN | G9: IQUIQUE | H9: BORDER | I9: 6 | J9: 5 | K9: NO
B10: 1 | C10: Tarapacá | D10: 1403 | E10: COLCHANE | F10: COE | G10: IQUIQUE | H10: BORDER | I10: 6 | J10: 5 | K10: NO
B11: 1 | C11: Tarapacá | D11: 1404 | E11: HUARA | F11: HRA | G11: IQUIQUE | H11: EXTREMA | I11: 5 | J11: 4 | K11: NO
B12: 1 | C12: Tarapacá | D12: 1101 | E12: IQUIQUE | F12: IQQ | G12: IQUIQUE | H12: BASE | I12: 3 | J12: 2 | K12: NO
B13: 1 | C13: Tarapacá | D13: 1405 | E13: PICA | F13: OPC | G13: IQUIQUE | H13: EXTREMA | I13: 5 | J13: 4 | K13: NO
B14: 1 | C14: Tarapacá | D14: 1401 | E14: POZO ALMONTE | F14: PAM | G14: IQUIQUE | H14: EXTREMA | I14: 5 | J14: 4 | K14: NO
B15: 2 | C15: Antofagasta | D15: 2101 | E15: ANTOFAGASTA | F15: ANF | G15: ANTOFAGASTA | H15: BASE | I15: 3 | J15: 2 | K15: NO
... B349: 12 | C349: Magallanes y la Antartica Chilena | D349: 12402 | E349: TORRES DEL PAINE | F349: TRP | G349: PUNTA ARENAS | H349: BORDER | I349: 15 | J349: 5 | K349: NO
